[{"AmountDue":1238.14,"AmountPayd":1806.56,"Customer":65,"Year":2018,"Month":7,"Amount":568.42},{"AmountDue":1152.74,"AmountPayd":1423.08,"Customer":14,"Year":2018,"Month":11,"Amount":270.34},{"AmountDue":1091.21,"AmountPayd":1578.68,"Customer":65,"Year":2018,"Month":1,"Amount":487.47},{"AmountDue":1076.04,"AmountPayd":1696.91,"Customer":30,"Year":2018,"Month":9,"Amount":620.87},{"AmountDue":1071.43,"AmountPayd":1126.52,"Customer":20,"Year":2018,"Month":8,"Amount":55.09},{"AmountDue":1018.17,"AmountPayd":1703.56,"Customer":58,"Year":2018,"Month":11,"Amount":685.39},{"AmountDue":1015.36,"AmountPayd":1326.66,"Customer":29,"Year":2018,"Month":11,"Amount":311.30},{"AmountDue":1012.14,"AmountPayd":1522.99,"Customer":6,"Year":2018,"Month":8,"Amount":510.85},{"AmountDue":1007.70,"AmountPayd":1499.67,"Customer":95,"Year":2018,"Month":4,"Amount":491.97},{"AmountDue":976.94,"AmountPayd":1677.63,"Customer":56,"Year":2018,"Month":11,"Amount":700.69},{"AmountDue":966.29,"AmountPayd":1806.56,"Customer":65,"Year":2018,"Month":7,"Amount":840.27},{"AmountDue":965.05,"AmountPayd":1264.87,"Customer":62,"Year":2018,"Month":2,"Amount":299.82},{"AmountDue":946.73,"AmountPayd":1609.53,"Customer":30,"Year":2018,"Month":10,"Amount":662.80},{"AmountDue":939.97,"AmountPayd":1680.58,"Customer":58,"Year":2018,"Month":3,"Amount":740.61},{"AmountDue":938.32,"AmountPayd":1374.65,"Customer":90,"Year":2018,"Month":11,"Amount":436.33},{"AmountDue":935.44,"AmountPayd":1269.50,"Customer":72,"Year":2018,"Month":11,"Amount":334.06},{"AmountDue":931.57,"AmountPayd":1456.32,"Customer":67,"Year":2018,"Month":7,"Amount":524.75},{"AmountDue":927.30,"AmountPayd":1571.22,"Customer":68,"Year":2018,"Month":6,"Amount":643.92},{"AmountDue":913.43,"AmountPayd":1289.32,"Customer":47,"Year":2018,"Month":2,"Amount":375.89},{"AmountDue":913.19,"AmountPayd":1410.66,"Customer":18,"Year":2018,"Month":12,"Amount":497.47},{"AmountDue":909.40,"AmountPayd":1018.62,"Customer":13,"Year":2018,"Month":10,"Amount":109.22},{"AmountDue":908.29,"AmountPayd":1214.22,"Customer":59,"Year":2018,"Month":4,"Amount":305.93},{"AmountDue":906.85,"AmountPayd":1567.32,"Customer":12,"Year":2018,"Month":10,"Amount":660.47},{"AmountDue":899.68,"AmountPayd":1314.21,"Customer":20,"Year":2018,"Month":4,"Amount":414.53},{"AmountDue":899.39,"AmountPayd":1594.97,"Customer":74,"Year":2018,"Month":9,"Amount":695.58},{"AmountDue":894.07,"AmountPayd":1084.20,"Customer":29,"Year":2018,"Month":6,"Amount":190.13},{"AmountDue":893.36,"AmountPayd":1296.23,"Customer":17,"Year":2018,"Month":11,"Amount":402.87},{"AmountDue":891.37,"AmountPayd":1680.58,"Customer":58,"Year":2018,"Month":3,"Amount":789.21},{"AmountDue":889.45,"AmountPayd":1246.99,"Customer":100,"Year":2018,"Month":2,"Amount":357.54},{"AmountDue":887.81,"AmountPayd":1237.71,"Customer":52,"Year":2018,"Month":3,"Amount":349.90},{"AmountDue":876.87,"AmountPayd":1554.75,"Customer":86,"Year":2018,"Month":2,"Amount":677.88},{"AmountDue":868.06,"AmountPayd":1307.86,"Customer":75,"Year":2018,"Month":2,"Amount":439.80},{"AmountDue":864.98,"AmountPayd":1089.20,"Customer":66,"Year":2018,"Month":7,"Amount":224.22},{"AmountDue":864.93,"AmountPayd":1404.53,"Customer":16,"Year":2018,"Month":5,"Amount":539.60},{"AmountDue":864.80,"AmountPayd":1609.92,"Customer":98,"Year":2018,"Month":1,"Amount":745.12},{"AmountDue":863.30,"AmountPayd":1216.68,"Customer":35,"Year":2018,"Month":11,"Amount":353.38},{"AmountDue":855.53,"AmountPayd":1297.57,"Customer":91,"Year":2018,"Month":10,"Amount":442.04},{"AmountDue":850.48,"AmountPayd":1278.31,"Customer":21,"Year":2018,"Month":3,"Amount":427.83},{"AmountDue":848.66,"AmountPayd":1696.91,"Customer":30,"Year":2018,"Month":9,"Amount":848.25},{"AmountDue":847.32,"AmountPayd":1567.32,"Customer":12,"Year":2018,"Month":10,"Amount":720.00},{"AmountDue":841.03,"AmountPayd":1309.87,"Customer":57,"Year":2018,"Month":5,"Amount":468.84},{"AmountDue":838.74,"AmountPayd":1575.00,"Customer":89,"Year":2018,"Month":5,"Amount":736.26},{"AmountDue":835.77,"AmountPayd":1244.28,"Customer":49,"Year":2018,"Month":9,"Amount":408.51},{"AmountDue":835.51,"AmountPayd":1303.25,"Customer":5,"Year":2018,"Month":8,"Amount":467.74},{"AmountDue":835.47,"AmountPayd":1522.84,"Customer":80,"Year":2018,"Month":1,"Amount":687.37},{"AmountDue":835.41,"AmountPayd":1429.05,"Customer":81,"Year":2018,"Month":3,"Amount":593.64},{"AmountDue":834.54,"AmountPayd":1554.75,"Customer":86,"Year":2018,"Month":2,"Amount":720.21},{"AmountDue":834.01,"AmountPayd":1000.95,"Customer":75,"Year":2018,"Month":1,"Amount":166.94},{"AmountDue":831.64,"AmountPayd":1120.10,"Customer":64,"Year":2018,"Month":4,"Amount":288.46},{"AmountDue":831.26,"AmountPayd":1375.97,"Customer":96,"Year":2018,"Month":10,"Amount":544.71},{"AmountDue":822.60,"AmountPayd":1631.75,"Customer":33,"Year":2018,"Month":5,"Amount":809.15},{"AmountDue":819.70,"AmountPayd":1278.31,"Customer":21,"Year":2018,"Month":3,"Amount":458.61},{"AmountDue":809.96,"AmountPayd":1220.69,"Customer":29,"Year":2018,"Month":1,"Amount":410.73},{"AmountDue":809.15,"AmountPayd":1631.75,"Customer":33,"Year":2018,"Month":5,"Amount":822.60},{"AmountDue":804.70,"AmountPayd":1024.02,"Customer":9,"Year":2018,"Month":10,"Amount":219.32},{"AmountDue":801.72,"AmountPayd":1329.24,"Customer":9,"Year":2018,"Month":7,"Amount":527.52},{"AmountDue":798.30,"AmountPayd":1406.01,"Customer":51,"Year":2018,"Month":11,"Amount":607.71},{"AmountDue":796.29,"AmountPayd":1547.66,"Customer":89,"Year":2018,"Month":3,"Amount":751.37},{"AmountDue":793.39,"AmountPayd":1077.24,"Customer":37,"Year":2018,"Month":1,"Amount":283.85},{"AmountDue":791.14,"AmountPayd":1293.60,"Customer":75,"Year":2018,"Month":11,"Amount":502.46},{"AmountDue":789.70,"AmountPayd":1026.67,"Customer":7,"Year":2018,"Month":9,"Amount":236.97},{"AmountDue":787.62,"AmountPayd":1178.69,"Customer":65,"Year":2018,"Month":12,"Amount":391.07},{"AmountDue":785.50,"AmountPayd":1035.18,"Customer":51,"Year":2018,"Month":9,"Amount":249.68},{"AmountDue":781.37,"AmountPayd":1090.24,"Customer":10,"Year":2018,"Month":3,"Amount":308.87},{"AmountDue":781.37,"AmountPayd":1058.85,"Customer":73,"Year":2018,"Month":8,"Amount":277.48},{"AmountDue":779.00,"AmountPayd":1353.92,"Customer":48,"Year":2018,"Month":8,"Amount":574.92},{"AmountDue":776.98,"AmountPayd":1241.04,"Customer":26,"Year":2018,"Month":6,"Amount":464.06},{"AmountDue":770.64,"AmountPayd":1314.60,"Customer":81,"Year":2018,"Month":11,"Amount":543.96},{"AmountDue":769.26,"AmountPayd":1373.25,"Customer":15,"Year":2018,"Month":2,"Amount":603.99},{"AmountDue":763.35,"AmountPayd":1114.26,"Customer":19,"Year":2018,"Month":1,"Amount":350.91},{"AmountDue":762.22,"AmountPayd":1522.84,"Customer":80,"Year":2018,"Month":1,"Amount":760.62},{"AmountDue":760.38,"AmountPayd":1226.42,"Customer":12,"Year":2018,"Month":12,"Amount":466.04},{"AmountDue":759.10,"AmountPayd":1224.48,"Customer":15,"Year":2018,"Month":4,"Amount":465.38},{"AmountDue":759.00,"AmountPayd":1191.35,"Customer":84,"Year":2018,"Month":8,"Amount":432.35},{"AmountDue":754.37,"AmountPayd":1241.04,"Customer":26,"Year":2018,"Month":6,"Amount":486.67},{"AmountDue":753.34,"AmountPayd":1490.15,"Customer":46,"Year":2018,"Month":12,"Amount":736.81},{"AmountDue":753.31,"AmountPayd":1703.56,"Customer":58,"Year":2018,"Month":11,"Amount":950.25},{"AmountDue":750.81,"AmountPayd":1032.36,"Customer":5,"Year":2018,"Month":5,"Amount":281.55},{"AmountDue":750.23,"AmountPayd":1292.08,"Customer":4,"Year":2018,"Month":5,"Amount":541.85},{"AmountDue":745.12,"AmountPayd":1609.92,"Customer":98,"Year":2018,"Month":1,"Amount":864.80},{"AmountDue":744.37,"AmountPayd":796.74,"Customer":58,"Year":2018,"Month":5,"Amount":52.37},{"AmountDue":744.18,"AmountPayd":1217.00,"Customer":83,"Year":2018,"Month":11,"Amount":472.82},{"AmountDue":743.77,"AmountPayd":1490.72,"Customer":12,"Year":2018,"Month":8,"Amount":746.95},{"AmountDue":742.85,"AmountPayd":1237.12,"Customer":100,"Year":2018,"Month":6,"Amount":494.27},{"AmountDue":741.75,"AmountPayd":1137.35,"Customer":20,"Year":2018,"Month":1,"Amount":395.60},{"AmountDue":736.81,"AmountPayd":1490.15,"Customer":46,"Year":2018,"Month":12,"Amount":753.34},{"AmountDue":736.63,"AmountPayd":1254.24,"Customer":62,"Year":2018,"Month":1,"Amount":517.61},{"AmountDue":735.50,"AmountPayd":1575.00,"Customer":89,"Year":2018,"Month":5,"Amount":839.50},{"AmountDue":731.74,"AmountPayd":1140.47,"Customer":67,"Year":2018,"Month":11,"Amount":408.73},{"AmountDue":730.12,"AmountPayd":1034.87,"Customer":52,"Year":2018,"Month":6,"Amount":304.75},{"AmountDue":729.05,"AmountPayd":1200.00,"Customer":22,"Year":2018,"Month":4,"Amount":470.95},{"AmountDue":726.99,"AmountPayd":1301.03,"Customer":76,"Year":2018,"Month":11,"Amount":574.04},{"AmountDue":724.95,"AmountPayd":1342.52,"Customer":1,"Year":2018,"Month":2,"Amount":617.57},{"AmountDue":722.06,"AmountPayd":1428.59,"Customer":26,"Year":2018,"Month":12,"Amount":706.53},{"AmountDue":720.45,"AmountPayd":1353.92,"Customer":48,"Year":2018,"Month":8,"Amount":633.47},{"AmountDue":706.53,"AmountPayd":1428.59,"Customer":26,"Year":2018,"Month":12,"Amount":722.06},{"AmountDue":705.06,"AmountPayd":910.40,"Customer":66,"Year":2018,"Month":5,"Amount":205.34},{"AmountDue":703.24,"AmountPayd":837.86,"Customer":4,"Year":2018,"Month":8,"Amount":134.62},{"AmountDue":701.95,"AmountPayd":1081.72,"Customer":51,"Year":2018,"Month":2,"Amount":379.77},{"AmountDue":700.69,"AmountPayd":1677.63,"Customer":56,"Year":2018,"Month":11,"Amount":976.94},{"AmountDue":697.26,"AmountPayd":1244.34,"Customer":88,"Year":2018,"Month":5,"Amount":547.08},{"AmountDue":695.58,"AmountPayd":1594.97,"Customer":74,"Year":2018,"Month":9,"Amount":899.39},{"AmountDue":692.63,"AmountPayd":1247.37,"Customer":22,"Year":2018,"Month":9,"Amount":554.74},{"AmountDue":692.13,"AmountPayd":1005.55,"Customer":55,"Year":2018,"Month":2,"Amount":313.42},{"AmountDue":690.86,"AmountPayd":1482.04,"Customer":31,"Year":2018,"Month":8,"Amount":791.18},{"AmountDue":689.17,"AmountPayd":1085.76,"Customer":61,"Year":2018,"Month":12,"Amount":396.59},{"AmountDue":684.86,"AmountPayd":1318.10,"Customer":20,"Year":2018,"Month":9,"Amount":633.24},{"AmountDue":683.30,"AmountPayd":1400.37,"Customer":38,"Year":2018,"Month":3,"Amount":717.07},{"AmountDue":678.14,"AmountPayd":1570.58,"Customer":95,"Year":2018,"Month":10,"Amount":892.44},{"AmountDue":677.33,"AmountPayd":1048.09,"Customer":57,"Year":2018,"Month":1,"Amount":370.76},{"AmountDue":676.07,"AmountPayd":788.76,"Customer":90,"Year":2018,"Month":1,"Amount":112.69},{"AmountDue":675.36,"AmountPayd":936.85,"Customer":100,"Year":2018,"Month":7,"Amount":261.49},{"AmountDue":671.98,"AmountPayd":1150.83,"Customer":69,"Year":2018,"Month":2,"Amount":478.85},{"AmountDue":669.80,"AmountPayd":878.53,"Customer":38,"Year":2018,"Month":2,"Amount":208.73},{"AmountDue":666.91,"AmountPayd":1202.06,"Customer":91,"Year":2018,"Month":1,"Amount":535.15},{"AmountDue":665.50,"AmountPayd":1110.75,"Customer":54,"Year":2018,"Month":8,"Amount":445.25},{"AmountDue":657.32,"AmountPayd":1326.66,"Customer":29,"Year":2018,"Month":11,"Amount":669.34},{"AmountDue":653.79,"AmountPayd":1609.53,"Customer":30,"Year":2018,"Month":10,"Amount":955.74},{"AmountDue":652.53,"AmountPayd":915.68,"Customer":12,"Year":2018,"Month":3,"Amount":263.15},{"AmountDue":649.06,"AmountPayd":981.79,"Customer":16,"Year":2018,"Month":8,"Amount":332.73},{"AmountDue":647.96,"AmountPayd":1053.15,"Customer":20,"Year":2018,"Month":2,"Amount":405.19},{"AmountDue":647.48,"AmountPayd":1195.79,"Customer":23,"Year":2018,"Month":12,"Amount":548.31},{"AmountDue":643.92,"AmountPayd":1571.22,"Customer":68,"Year":2018,"Month":6,"Amount":927.30},{"AmountDue":641.94,"AmountPayd":1143.06,"Customer":61,"Year":2018,"Month":8,"Amount":501.12},{"AmountDue":641.84,"AmountPayd":988.91,"Customer":39,"Year":2018,"Month":5,"Amount":347.07},{"AmountDue":641.50,"AmountPayd":1223.06,"Customer":14,"Year":2018,"Month":7,"Amount":581.56},{"AmountDue":641.01,"AmountPayd":1226.16,"Customer":79,"Year":2018,"Month":9,"Amount":585.15},{"AmountDue":640.49,"AmountPayd":1243.15,"Customer":92,"Year":2018,"Month":5,"Amount":602.66},{"AmountDue":640.36,"AmountPayd":1338.83,"Customer":84,"Year":2018,"Month":2,"Amount":698.47},{"AmountDue":639.84,"AmountPayd":961.77,"Customer":80,"Year":2018,"Month":10,"Amount":321.93},{"AmountDue":639.18,"AmountPayd":1247.37,"Customer":22,"Year":2018,"Month":9,"Amount":608.19},{"AmountDue":638.83,"AmountPayd":1161.31,"Customer":85,"Year":2018,"Month":12,"Amount":522.48},{"AmountDue":637.99,"AmountPayd":1149.86,"Customer":89,"Year":2018,"Month":11,"Amount":511.87},{"AmountDue":635.95,"AmountPayd":808.38,"Customer":52,"Year":2018,"Month":4,"Amount":172.43},{"AmountDue":633.96,"AmountPayd":1131.14,"Customer":91,"Year":2018,"Month":8,"Amount":497.18},{"AmountDue":632.36,"AmountPayd":1024.02,"Customer":9,"Year":2018,"Month":10,"Amount":391.66},{"AmountDue":631.67,"AmountPayd":1202.51,"Customer":50,"Year":2018,"Month":10,"Amount":570.84},{"AmountDue":626.71,"AmountPayd":1243.12,"Customer":67,"Year":2018,"Month":8,"Amount":616.41},{"AmountDue":622.78,"AmountPayd":1269.50,"Customer":72,"Year":2018,"Month":11,"Amount":646.72},{"AmountDue":621.41,"AmountPayd":1211.11,"Customer":42,"Year":2018,"Month":5,"Amount":589.70},{"AmountDue":618.40,"AmountPayd":1138.60,"Customer":66,"Year":2018,"Month":8,"Amount":520.20},{"AmountDue":617.57,"AmountPayd":1342.52,"Customer":1,"Year":2018,"Month":2,"Amount":724.95},{"AmountDue":616.00,"AmountPayd":1338.83,"Customer":84,"Year":2018,"Month":2,"Amount":722.83},{"AmountDue":615.77,"AmountPayd":787.29,"Customer":39,"Year":2018,"Month":1,"Amount":171.52},{"AmountDue":614.80,"AmountPayd":911.75,"Customer":19,"Year":2018,"Month":2,"Amount":296.95},{"AmountDue":613.62,"AmountPayd":1098.40,"Customer":78,"Year":2018,"Month":8,"Amount":484.78},{"AmountDue":612.55,"AmountPayd":1352.27,"Customer":40,"Year":2018,"Month":7,"Amount":739.72},{"AmountDue":611.68,"AmountPayd":1063.62,"Customer":20,"Year":2018,"Month":5,"Amount":451.94},{"AmountDue":610.37,"AmountPayd":1083.37,"Customer":76,"Year":2018,"Month":7,"Amount":473.00},{"AmountDue":607.71,"AmountPayd":1406.01,"Customer":51,"Year":2018,"Month":11,"Amount":798.30},{"AmountDue":606.91,"AmountPayd":1077.24,"Customer":37,"Year":2018,"Month":1,"Amount":470.33},{"AmountDue":606.68,"AmountPayd":963.75,"Customer":95,"Year":2018,"Month":12,"Amount":357.07},{"AmountDue":606.60,"AmountPayd":1024.60,"Customer":60,"Year":2018,"Month":12,"Amount":418.00},{"AmountDue":606.41,"AmountPayd":792.93,"Customer":29,"Year":2018,"Month":7,"Amount":186.52},{"AmountDue":605.14,"AmountPayd":1244.34,"Customer":88,"Year":2018,"Month":5,"Amount":639.20},{"AmountDue":604.66,"AmountPayd":1388.95,"Customer":49,"Year":2018,"Month":2,"Amount":784.29},{"AmountDue":603.14,"AmountPayd":1522.99,"Customer":6,"Year":2018,"Month":8,"Amount":919.85},{"AmountDue":602.66,"AmountPayd":1243.15,"Customer":92,"Year":2018,"Month":5,"Amount":640.49},{"AmountDue":599.88,"AmountPayd":1070.91,"Customer":27,"Year":2018,"Month":3,"Amount":471.03},{"AmountDue":599.27,"AmountPayd":1224.48,"Customer":15,"Year":2018,"Month":4,"Amount":625.21},{"AmountDue":599.27,"AmountPayd":1499.67,"Customer":95,"Year":2018,"Month":4,"Amount":900.40},{"AmountDue":597.79,"AmountPayd":1094.99,"Customer":29,"Year":2018,"Month":5,"Amount":497.20},{"AmountDue":597.06,"AmountPayd":890.04,"Customer":79,"Year":2018,"Month":5,"Amount":292.98},{"AmountDue":596.48,"AmountPayd":795.28,"Customer":82,"Year":2018,"Month":6,"Amount":198.80},{"AmountDue":595.02,"AmountPayd":1482.04,"Customer":31,"Year":2018,"Month":8,"Amount":887.02},{"AmountDue":593.64,"AmountPayd":1429.05,"Customer":81,"Year":2018,"Month":3,"Amount":835.41},{"AmountDue":592.12,"AmountPayd":1394.89,"Customer":2,"Year":2018,"Month":6,"Amount":802.77},{"AmountDue":591.07,"AmountPayd":951.64,"Customer":82,"Year":2018,"Month":10,"Amount":360.57},{"AmountDue":590.97,"AmountPayd":1124.51,"Customer":87,"Year":2018,"Month":11,"Amount":533.54},{"AmountDue":590.82,"AmountPayd":893.88,"Customer":21,"Year":2018,"Month":7,"Amount":303.06},{"AmountDue":590.06,"AmountPayd":734.72,"Customer":31,"Year":2018,"Month":7,"Amount":144.66},{"AmountDue":589.70,"AmountPayd":1211.11,"Customer":42,"Year":2018,"Month":5,"Amount":621.41},{"AmountDue":589.11,"AmountPayd":1075.38,"Customer":70,"Year":2018,"Month":5,"Amount":486.27},{"AmountDue":588.95,"AmountPayd":1053.80,"Customer":64,"Year":2018,"Month":2,"Amount":464.85},{"AmountDue":588.91,"AmountPayd":1388.95,"Customer":49,"Year":2018,"Month":2,"Amount":800.04},{"AmountDue":588.00,"AmountPayd":1111.37,"Customer":39,"Year":2018,"Month":12,"Amount":523.37},{"AmountDue":587.64,"AmountPayd":1319.39,"Customer":47,"Year":2018,"Month":11,"Amount":731.75},{"AmountDue":585.83,"AmountPayd":1411.37,"Customer":68,"Year":2018,"Month":7,"Amount":825.54},{"AmountDue":585.63,"AmountPayd":951.64,"Customer":82,"Year":2018,"Month":10,"Amount":366.01},{"AmountDue":580.93,"AmountPayd":1049.03,"Customer":73,"Year":2018,"Month":12,"Amount":468.10},{"AmountDue":580.39,"AmountPayd":817.87,"Customer":86,"Year":2018,"Month":6,"Amount":237.48},{"AmountDue":578.79,"AmountPayd":856.26,"Customer":60,"Year":2018,"Month":9,"Amount":277.47},{"AmountDue":578.72,"AmountPayd":992.89,"Customer":58,"Year":2018,"Month":8,"Amount":414.17},{"AmountDue":578.48,"AmountPayd":1154.04,"Customer":18,"Year":2018,"Month":3,"Amount":575.56},{"AmountDue":575.08,"AmountPayd":1078.01,"Customer":54,"Year":2018,"Month":2,"Amount":502.93},{"AmountDue":572.62,"AmountPayd":921.01,"Customer":31,"Year":2018,"Month":4,"Amount":348.39},{"AmountDue":572.36,"AmountPayd":834.79,"Customer":18,"Year":2018,"Month":10,"Amount":262.43},{"AmountDue":572.35,"AmountPayd":1006.02,"Customer":41,"Year":2018,"Month":8,"Amount":433.67},{"AmountDue":570.87,"AmountPayd":907.94,"Customer":60,"Year":2018,"Month":10,"Amount":337.07},{"AmountDue":570.84,"AmountPayd":1202.51,"Customer":50,"Year":2018,"Month":10,"Amount":631.67},{"AmountDue":567.13,"AmountPayd":1078.61,"Customer":98,"Year":2018,"Month":4,"Amount":511.48},{"AmountDue":564.61,"AmountPayd":1070.96,"Customer":84,"Year":2018,"Month":3,"Amount":506.35},{"AmountDue":563.76,"AmountPayd":1017.93,"Customer":61,"Year":2018,"Month":2,"Amount":454.17},{"AmountDue":561.96,"AmountPayd":1194.80,"Customer":35,"Year":2018,"Month":8,"Amount":632.84},{"AmountDue":560.78,"AmountPayd":921.01,"Customer":31,"Year":2018,"Month":4,"Amount":360.23},{"AmountDue":560.23,"AmountPayd":1118.48,"Customer":98,"Year":2018,"Month":9,"Amount":558.25},{"AmountDue":558.25,"AmountPayd":1118.48,"Customer":98,"Year":2018,"Month":9,"Amount":560.23},{"AmountDue":558.13,"AmountPayd":709.46,"Customer":17,"Year":2018,"Month":5,"Amount":151.33},{"AmountDue":554.49,"AmountPayd":1276.93,"Customer":33,"Year":2018,"Month":8,"Amount":722.44},{"AmountDue":554.48,"AmountPayd":827.75,"Customer":11,"Year":2018,"Month":7,"Amount":273.27},{"AmountDue":554.34,"AmountPayd":1045.11,"Customer":9,"Year":2018,"Month":5,"Amount":490.77},{"AmountDue":553.69,"AmountPayd":1108.35,"Customer":6,"Year":2018,"Month":9,"Amount":554.66},{"AmountDue":546.26,"AmountPayd":912.00,"Customer":39,"Year":2018,"Month":7,"Amount":365.74},{"AmountDue":545.43,"AmountPayd":1195.79,"Customer":23,"Year":2018,"Month":12,"Amount":650.36},{"AmountDue":544.73,"AmountPayd":1570.58,"Customer":95,"Year":2018,"Month":10,"Amount":1025.85},{"AmountDue":544.71,"AmountPayd":1375.97,"Customer":96,"Year":2018,"Month":10,"Amount":831.26},{"AmountDue":544.46,"AmountPayd":940.40,"Customer":49,"Year":2018,"Month":5,"Amount":395.94},{"AmountDue":540.50,"AmountPayd":1373.25,"Customer":15,"Year":2018,"Month":2,"Amount":832.75},{"AmountDue":540.29,"AmountPayd":1447.73,"Customer":80,"Year":2018,"Month":6,"Amount":907.44},{"AmountDue":539.60,"AmountPayd":1404.53,"Customer":16,"Year":2018,"Month":5,"Amount":864.93},{"AmountDue":537.95,"AmountPayd":888.49,"Customer":32,"Year":2018,"Month":6,"Amount":350.54},{"AmountDue":535.67,"AmountPayd":697.77,"Customer":35,"Year":2018,"Month":1,"Amount":162.10},{"AmountDue":535.23,"AmountPayd":1319.23,"Customer":97,"Year":2018,"Month":7,"Amount":784.00},{"AmountDue":535.15,"AmountPayd":1202.06,"Customer":91,"Year":2018,"Month":1,"Amount":666.91},{"AmountDue":534.56,"AmountPayd":1042.71,"Customer":33,"Year":2018,"Month":3,"Amount":508.15},{"AmountDue":534.16,"AmountPayd":956.66,"Customer":54,"Year":2018,"Month":1,"Amount":422.50},{"AmountDue":530.23,"AmountPayd":1258.10,"Customer":38,"Year":2018,"Month":11,"Amount":727.87},{"AmountDue":529.33,"AmountPayd":893.88,"Customer":21,"Year":2018,"Month":7,"Amount":364.55},{"AmountDue":527.81,"AmountPayd":836.95,"Customer":77,"Year":2018,"Month":4,"Amount":309.14},{"AmountDue":527.38,"AmountPayd":820.53,"Customer":16,"Year":2018,"Month":11,"Amount":293.15},{"AmountDue":526.75,"AmountPayd":975.12,"Customer":100,"Year":2018,"Month":4,"Amount":448.37},{"AmountDue":526.04,"AmountPayd":964.45,"Customer":7,"Year":2018,"Month":11,"Amount":438.41},{"AmountDue":523.37,"AmountPayd":1111.37,"Customer":39,"Year":2018,"Month":12,"Amount":588.00},{"AmountDue":520.57,"AmountPayd":796.47,"Customer":20,"Year":2018,"Month":11,"Amount":275.90},{"AmountDue":520.20,"AmountPayd":1138.60,"Customer":66,"Year":2018,"Month":8,"Amount":618.40},{"AmountDue":519.79,"AmountPayd":888.60,"Customer":66,"Year":2018,"Month":6,"Amount":368.81},{"AmountDue":518.17,"AmountPayd":1450.90,"Customer":7,"Year":2018,"Month":12,"Amount":932.73},{"AmountDue":517.61,"AmountPayd":1254.24,"Customer":62,"Year":2018,"Month":1,"Amount":736.63},{"AmountDue":514.42,"AmountPayd":1012.51,"Customer":7,"Year":2018,"Month":4,"Amount":498.09},{"AmountDue":513.79,"AmountPayd":1547.66,"Customer":89,"Year":2018,"Month":3,"Amount":1033.87},{"AmountDue":512.79,"AmountPayd":860.99,"Customer":86,"Year":2018,"Month":5,"Amount":348.20},{"AmountDue":511.87,"AmountPayd":1149.86,"Customer":89,"Year":2018,"Month":11,"Amount":637.99},{"AmountDue":511.56,"AmountPayd":1243.12,"Customer":67,"Year":2018,"Month":8,"Amount":731.56},{"AmountDue":511.03,"AmountPayd":1319.23,"Customer":97,"Year":2018,"Month":7,"Amount":808.20},{"AmountDue":509.89,"AmountPayd":1299.61,"Customer":44,"Year":2018,"Month":12,"Amount":789.72},{"AmountDue":509.70,"AmountPayd":1325.32,"Customer":26,"Year":2018,"Month":1,"Amount":815.62},{"AmountDue":507.72,"AmountPayd":916.26,"Customer":42,"Year":2018,"Month":9,"Amount":408.54},{"AmountDue":504.32,"AmountPayd":710.14,"Customer":30,"Year":2018,"Month":6,"Amount":205.82},{"AmountDue":503.82,"AmountPayd":740.95,"Customer":6,"Year":2018,"Month":12,"Amount":237.13},{"AmountDue":503.59,"AmountPayd":1160.65,"Customer":62,"Year":2018,"Month":6,"Amount":657.06},{"AmountDue":503.52,"AmountPayd":1070.96,"Customer":84,"Year":2018,"Month":3,"Amount":567.44},{"AmountDue":502.46,"AmountPayd":1293.60,"Customer":75,"Year":2018,"Month":11,"Amount":791.14},{"AmountDue":501.02,"AmountPayd":1352.27,"Customer":40,"Year":2018,"Month":7,"Amount":851.25},{"AmountDue":500.62,"AmountPayd":1275.77,"Customer":71,"Year":2018,"Month":8,"Amount":775.15},{"AmountDue":498.09,"AmountPayd":1012.51,"Customer":7,"Year":2018,"Month":4,"Amount":514.42},{"AmountDue":497.61,"AmountPayd":1132.50,"Customer":95,"Year":2018,"Month":7,"Amount":634.89},{"AmountDue":497.47,"AmountPayd":1410.66,"Customer":18,"Year":2018,"Month":12,"Amount":913.19},{"AmountDue":497.20,"AmountPayd":1094.99,"Customer":29,"Year":2018,"Month":5,"Amount":597.79},{"AmountDue":497.18,"AmountPayd":1258.10,"Customer":38,"Year":2018,"Month":11,"Amount":760.92},{"AmountDue":497.18,"AmountPayd":1131.14,"Customer":91,"Year":2018,"Month":8,"Amount":633.96},{"AmountDue":497.00,"AmountPayd":1490.72,"Customer":12,"Year":2018,"Month":8,"Amount":993.72},{"AmountDue":496.79,"AmountPayd":742.91,"Customer":97,"Year":2018,"Month":3,"Amount":246.12},{"AmountDue":496.28,"AmountPayd":1125.93,"Customer":50,"Year":2018,"Month":6,"Amount":629.65},{"AmountDue":496.18,"AmountPayd":1314.60,"Customer":81,"Year":2018,"Month":11,"Amount":818.42},{"AmountDue":495.37,"AmountPayd":762.90,"Customer":55,"Year":2018,"Month":1,"Amount":267.53},{"AmountDue":494.76,"AmountPayd":1578.68,"Customer":65,"Year":2018,"Month":1,"Amount":1083.92},{"AmountDue":494.66,"AmountPayd":1329.24,"Customer":9,"Year":2018,"Month":7,"Amount":834.58},{"AmountDue":490.80,"AmountPayd":1309.87,"Customer":57,"Year":2018,"Month":5,"Amount":819.07},{"AmountDue":490.77,"AmountPayd":1045.11,"Customer":9,"Year":2018,"Month":5,"Amount":554.34},{"AmountDue":489.25,"AmountPayd":854.10,"Customer":11,"Year":2018,"Month":2,"Amount":364.85},{"AmountDue":488.91,"AmountPayd":1312.23,"Customer":79,"Year":2018,"Month":8,"Amount":823.32},{"AmountDue":487.68,"AmountPayd":951.19,"Customer":81,"Year":2018,"Month":5,"Amount":463.51},{"AmountDue":487.64,"AmountPayd":616.58,"Customer":54,"Year":2018,"Month":9,"Amount":128.94},{"AmountDue":485.62,"AmountPayd":902.76,"Customer":90,"Year":2018,"Month":12,"Amount":417.14},{"AmountDue":485.05,"AmountPayd":1165.18,"Customer":68,"Year":2018,"Month":9,"Amount":680.13},{"AmountDue":484.91,"AmountPayd":883.86,"Customer":93,"Year":2018,"Month":2,"Amount":398.95},{"AmountDue":484.34,"AmountPayd":880.44,"Customer":34,"Year":2018,"Month":5,"Amount":396.10},{"AmountDue":483.07,"AmountPayd":1271.64,"Customer":70,"Year":2018,"Month":8,"Amount":788.57},{"AmountDue":482.10,"AmountPayd":719.64,"Customer":8,"Year":2018,"Month":11,"Amount":237.54},{"AmountDue":479.61,"AmountPayd":1085.14,"Customer":94,"Year":2018,"Month":6,"Amount":605.53},{"AmountDue":477.02,"AmountPayd":555.57,"Customer":34,"Year":2018,"Month":4,"Amount":78.55},{"AmountDue":476.82,"AmountPayd":1124.51,"Customer":87,"Year":2018,"Month":11,"Amount":647.69},{"AmountDue":476.10,"AmountPayd":800.53,"Customer":16,"Year":2018,"Month":2,"Amount":324.43},{"AmountDue":475.67,"AmountPayd":974.33,"Customer":48,"Year":2018,"Month":12,"Amount":498.66},{"AmountDue":475.51,"AmountPayd":1068.62,"Customer":28,"Year":2018,"Month":1,"Amount":593.11},{"AmountDue":473.95,"AmountPayd":878.53,"Customer":38,"Year":2018,"Month":2,"Amount":404.58},{"AmountDue":473.43,"AmountPayd":1154.58,"Customer":1,"Year":2018,"Month":6,"Amount":681.15},{"AmountDue":473.29,"AmountPayd":917.37,"Customer":29,"Year":2018,"Month":4,"Amount":444.08},{"AmountDue":473.00,"AmountPayd":1083.37,"Customer":76,"Year":2018,"Month":7,"Amount":610.37},{"AmountDue":472.82,"AmountPayd":1217.00,"Customer":83,"Year":2018,"Month":11,"Amount":744.18},{"AmountDue":470.72,"AmountPayd":1099.55,"Customer":34,"Year":2018,"Month":8,"Amount":628.83},{"AmountDue":469.75,"AmountPayd":1078.82,"Customer":94,"Year":2018,"Month":3,"Amount":609.07},{"AmountDue":469.55,"AmountPayd":997.84,"Customer":87,"Year":2018,"Month":9,"Amount":528.29},{"AmountDue":467.74,"AmountPayd":1303.25,"Customer":5,"Year":2018,"Month":8,"Amount":835.51},{"AmountDue":466.90,"AmountPayd":1001.91,"Customer":36,"Year":2018,"Month":6,"Amount":535.01},{"AmountDue":466.20,"AmountPayd":790.85,"Customer":27,"Year":2018,"Month":11,"Amount":324.65},{"AmountDue":466.04,"AmountPayd":1226.42,"Customer":12,"Year":2018,"Month":12,"Amount":760.38},{"AmountDue":465.99,"AmountPayd":1271.64,"Customer":70,"Year":2018,"Month":8,"Amount":805.65},{"AmountDue":464.61,"AmountPayd":1219.60,"Customer":92,"Year":2018,"Month":11,"Amount":754.99},{"AmountDue":464.46,"AmountPayd":1060.55,"Customer":6,"Year":2018,"Month":5,"Amount":596.09},{"AmountDue":464.36,"AmountPayd":961.76,"Customer":43,"Year":2018,"Month":8,"Amount":497.40},{"AmountDue":464.10,"AmountPayd":687.16,"Customer":34,"Year":2018,"Month":10,"Amount":223.06},{"AmountDue":463.96,"AmountPayd":702.08,"Customer":25,"Year":2018,"Month":9,"Amount":238.12},{"AmountDue":463.51,"AmountPayd":951.19,"Customer":81,"Year":2018,"Month":5,"Amount":487.68},{"AmountDue":463.42,"AmountPayd":1117.53,"Customer":94,"Year":2018,"Month":12,"Amount":654.11},{"AmountDue":463.04,"AmountPayd":1200.00,"Customer":22,"Year":2018,"Month":4,"Amount":736.96},{"AmountDue":462.48,"AmountPayd":1107.58,"Customer":15,"Year":2018,"Month":8,"Amount":645.10},{"AmountDue":462.48,"AmountPayd":1007.19,"Customer":24,"Year":2018,"Month":1,"Amount":544.71},{"AmountDue":460.26,"AmountPayd":1347.18,"Customer":87,"Year":2018,"Month":3,"Amount":886.92},{"AmountDue":457.74,"AmountPayd":746.17,"Customer":64,"Year":2018,"Month":6,"Amount":288.43},{"AmountDue":457.51,"AmountPayd":670.00,"Customer":18,"Year":2018,"Month":2,"Amount":212.49},{"AmountDue":457.14,"AmountPayd":1132.50,"Customer":95,"Year":2018,"Month":7,"Amount":675.36},{"AmountDue":455.25,"AmountPayd":790.85,"Customer":27,"Year":2018,"Month":11,"Amount":335.60},{"AmountDue":455.18,"AmountPayd":1301.03,"Customer":76,"Year":2018,"Month":11,"Amount":845.85},{"AmountDue":455.05,"AmountPayd":1162.69,"Customer":92,"Year":2018,"Month":6,"Amount":707.64},{"AmountDue":454.68,"AmountPayd":733.01,"Customer":63,"Year":2018,"Month":2,"Amount":278.33},{"AmountDue":454.45,"AmountPayd":690.64,"Customer":35,"Year":2018,"Month":10,"Amount":236.19},{"AmountDue":454.17,"AmountPayd":1017.93,"Customer":61,"Year":2018,"Month":2,"Amount":563.76},{"AmountDue":451.96,"AmountPayd":789.01,"Customer":76,"Year":2018,"Month":12,"Amount":337.05},{"AmountDue":451.51,"AmountPayd":763.28,"Customer":59,"Year":2018,"Month":10,"Amount":311.77},{"AmountDue":450.14,"AmountPayd":738.04,"Customer":56,"Year":2018,"Month":5,"Amount":287.90},{"AmountDue":449.94,"AmountPayd":1210.89,"Customer":99,"Year":2018,"Month":9,"Amount":760.95},{"AmountDue":449.71,"AmountPayd":1083.13,"Customer":80,"Year":2018,"Month":8,"Amount":633.42},{"AmountDue":449.12,"AmountPayd":1126.52,"Customer":20,"Year":2018,"Month":8,"Amount":677.40},{"AmountDue":448.31,"AmountPayd":970.79,"Customer":76,"Year":2018,"Month":2,"Amount":522.48},{"AmountDue":447.96,"AmountPayd":1292.08,"Customer":4,"Year":2018,"Month":5,"Amount":844.12},{"AmountDue":446.78,"AmountPayd":1035.18,"Customer":51,"Year":2018,"Month":9,"Amount":588.40},{"AmountDue":444.72,"AmountPayd":1299.61,"Customer":44,"Year":2018,"Month":12,"Amount":854.89},{"AmountDue":442.34,"AmountPayd":1194.80,"Customer":35,"Year":2018,"Month":8,"Amount":752.46},{"AmountDue":442.04,"AmountPayd":854.70,"Customer":16,"Year":2018,"Month":1,"Amount":412.66},{"AmountDue":442.04,"AmountPayd":1297.57,"Customer":91,"Year":2018,"Month":10,"Amount":855.53},{"AmountDue":441.99,"AmountPayd":600.84,"Customer":63,"Year":2018,"Month":4,"Amount":158.85},{"AmountDue":441.96,"AmountPayd":695.85,"Customer":67,"Year":2018,"Month":2,"Amount":253.89},{"AmountDue":441.47,"AmountPayd":861.38,"Customer":92,"Year":2018,"Month":2,"Amount":419.91},{"AmountDue":439.80,"AmountPayd":1307.86,"Customer":75,"Year":2018,"Month":2,"Amount":868.06},{"AmountDue":436.33,"AmountPayd":1374.65,"Customer":90,"Year":2018,"Month":11,"Amount":938.32},{"AmountDue":433.76,"AmountPayd":862.33,"Customer":89,"Year":2018,"Month":8,"Amount":428.57},{"AmountDue":433.67,"AmountPayd":1006.02,"Customer":41,"Year":2018,"Month":8,"Amount":572.35},{"AmountDue":433.11,"AmountPayd":581.33,"Customer":27,"Year":2018,"Month":6,"Amount":148.22},{"AmountDue":433.03,"AmountPayd":1150.83,"Customer":69,"Year":2018,"Month":2,"Amount":717.80},{"AmountDue":432.35,"AmountPayd":1191.35,"Customer":84,"Year":2018,"Month":8,"Amount":759.00},{"AmountDue":432.34,"AmountPayd":837.28,"Customer":83,"Year":2018,"Month":2,"Amount":404.94},{"AmountDue":431.94,"AmountPayd":1032.36,"Customer":5,"Year":2018,"Month":5,"Amount":600.42},{"AmountDue":431.90,"AmountPayd":997.94,"Customer":6,"Year":2018,"Month":1,"Amount":566.04},{"AmountDue":431.10,"AmountPayd":913.38,"Customer":68,"Year":2018,"Month":12,"Amount":482.28},{"AmountDue":429.35,"AmountPayd":868.09,"Customer":29,"Year":2018,"Month":12,"Amount":438.74},{"AmountDue":428.30,"AmountPayd":930.78,"Customer":47,"Year":2018,"Month":10,"Amount":502.48},{"AmountDue":426.21,"AmountPayd":1232.39,"Customer":67,"Year":2018,"Month":4,"Amount":806.18},{"AmountDue":425.37,"AmountPayd":1041.22,"Customer":33,"Year":2018,"Month":11,"Amount":615.85},{"AmountDue":424.73,"AmountPayd":637.86,"Customer":82,"Year":2018,"Month":8,"Amount":213.13},{"AmountDue":422.93,"AmountPayd":997.94,"Customer":6,"Year":2018,"Month":1,"Amount":575.01},{"AmountDue":422.66,"AmountPayd":964.09,"Customer":1,"Year":2018,"Month":5,"Amount":541.43},{"AmountDue":420.13,"AmountPayd":649.10,"Customer":8,"Year":2018,"Month":3,"Amount":228.97},{"AmountDue":419.82,"AmountPayd":1246.60,"Customer":38,"Year":2018,"Month":8,"Amount":826.78},{"AmountDue":419.33,"AmountPayd":606.83,"Customer":57,"Year":2018,"Month":7,"Amount":187.50},{"AmountDue":419.07,"AmountPayd":1117.53,"Customer":94,"Year":2018,"Month":12,"Amount":698.46},{"AmountDue":417.22,"AmountPayd":1276.93,"Customer":33,"Year":2018,"Month":8,"Amount":859.71},{"AmountDue":417.14,"AmountPayd":902.76,"Customer":90,"Year":2018,"Month":12,"Amount":485.62},{"AmountDue":416.83,"AmountPayd":686.65,"Customer":87,"Year":2018,"Month":2,"Amount":269.82},{"AmountDue":416.54,"AmountPayd":855.19,"Customer":71,"Year":2018,"Month":4,"Amount":438.65},{"AmountDue":416.02,"AmountPayd":1010.09,"Customer":28,"Year":2018,"Month":6,"Amount":594.07},{"AmountDue":414.53,"AmountPayd":1314.21,"Customer":20,"Year":2018,"Month":4,"Amount":899.68},{"AmountDue":413.26,"AmountPayd":1237.12,"Customer":100,"Year":2018,"Month":6,"Amount":823.86},{"AmountDue":413.18,"AmountPayd":1021.88,"Customer":71,"Year":2018,"Month":12,"Amount":608.70},{"AmountDue":412.98,"AmountPayd":1007.19,"Customer":24,"Year":2018,"Month":1,"Amount":594.21},{"AmountDue":412.66,"AmountPayd":854.70,"Customer":16,"Year":2018,"Month":1,"Amount":442.04},{"AmountDue":411.96,"AmountPayd":833.31,"Customer":67,"Year":2018,"Month":10,"Amount":421.35},{"AmountDue":411.79,"AmountPayd":784.01,"Customer":79,"Year":2018,"Month":3,"Amount":372.22},{"AmountDue":409.84,"AmountPayd":1001.91,"Customer":36,"Year":2018,"Month":6,"Amount":592.07},{"AmountDue":409.79,"AmountPayd":1096.37,"Customer":36,"Year":2018,"Month":3,"Amount":686.58},{"AmountDue":409.44,"AmountPayd":1096.37,"Customer":36,"Year":2018,"Month":3,"Amount":686.93},{"AmountDue":409.30,"AmountPayd":681.57,"Customer":8,"Year":2018,"Month":10,"Amount":272.27},{"AmountDue":408.73,"AmountPayd":1140.47,"Customer":67,"Year":2018,"Month":11,"Amount":731.74},{"AmountDue":408.51,"AmountPayd":1244.28,"Customer":49,"Year":2018,"Month":9,"Amount":835.77},{"AmountDue":408.45,"AmountPayd":910.42,"Customer":24,"Year":2018,"Month":2,"Amount":501.97},{"AmountDue":405.50,"AmountPayd":1223.06,"Customer":14,"Year":2018,"Month":7,"Amount":817.56},{"AmountDue":405.43,"AmountPayd":1220.09,"Customer":78,"Year":2018,"Month":11,"Amount":814.66},{"AmountDue":405.26,"AmountPayd":1075.38,"Customer":70,"Year":2018,"Month":5,"Amount":670.12},{"AmountDue":405.19,"AmountPayd":1053.15,"Customer":20,"Year":2018,"Month":2,"Amount":647.96},{"AmountDue":404.52,"AmountPayd":1026.46,"Customer":23,"Year":2018,"Month":7,"Amount":621.94},{"AmountDue":404.07,"AmountPayd":1456.32,"Customer":67,"Year":2018,"Month":7,"Amount":1052.25},{"AmountDue":402.87,"AmountPayd":1296.23,"Customer":17,"Year":2018,"Month":11,"Amount":893.36},{"AmountDue":402.40,"AmountPayd":627.21,"Customer":74,"Year":2018,"Month":5,"Amount":224.81},{"AmountDue":401.67,"AmountPayd":1210.89,"Customer":99,"Year":2018,"Month":9,"Amount":809.22},{"AmountDue":401.57,"AmountPayd":1053.80,"Customer":64,"Year":2018,"Month":2,"Amount":652.23},{"AmountDue":399.87,"AmountPayd":1078.61,"Customer":98,"Year":2018,"Month":4,"Amount":678.74},{"AmountDue":399.05,"AmountPayd":1083.13,"Customer":80,"Year":2018,"Month":8,"Amount":684.08},{"AmountDue":398.95,"AmountPayd":883.86,"Customer":93,"Year":2018,"Month":2,"Amount":484.91},{"AmountDue":398.08,"AmountPayd":1275.77,"Customer":71,"Year":2018,"Month":8,"Amount":877.69},{"AmountDue":397.72,"AmountPayd":763.43,"Customer":36,"Year":2018,"Month":12,"Amount":365.71},{"AmountDue":397.28,"AmountPayd":968.77,"Customer":17,"Year":2018,"Month":8,"Amount":571.49},{"AmountDue":396.10,"AmountPayd":880.44,"Customer":34,"Year":2018,"Month":5,"Amount":484.34},{"AmountDue":394.74,"AmountPayd":1016.84,"Customer":35,"Year":2018,"Month":3,"Amount":622.10},{"AmountDue":393.55,"AmountPayd":986.89,"Customer":79,"Year":2018,"Month":6,"Amount":593.34},{"AmountDue":391.07,"AmountPayd":1178.69,"Customer":65,"Year":2018,"Month":12,"Amount":787.62},{"AmountDue":390.94,"AmountPayd":766.29,"Customer":91,"Year":2018,"Month":9,"Amount":375.35},{"AmountDue":388.58,"AmountPayd":847.11,"Customer":93,"Year":2018,"Month":12,"Amount":458.53},{"AmountDue":388.41,"AmountPayd":745.24,"Customer":43,"Year":2018,"Month":4,"Amount":356.83},{"AmountDue":388.18,"AmountPayd":1460.54,"Customer":52,"Year":2018,"Month":9,"Amount":1072.36},{"AmountDue":387.02,"AmountPayd":787.09,"Customer":96,"Year":2018,"Month":3,"Amount":400.07},{"AmountDue":386.21,"AmountPayd":763.87,"Customer":69,"Year":2018,"Month":12,"Amount":377.66},{"AmountDue":385.55,"AmountPayd":575.88,"Customer":31,"Year":2018,"Month":3,"Amount":190.33},{"AmountDue":385.00,"AmountPayd":728.33,"Customer":6,"Year":2018,"Month":4,"Amount":343.33},{"AmountDue":384.60,"AmountPayd":609.10,"Customer":37,"Year":2018,"Month":5,"Amount":224.50},{"AmountDue":384.45,"AmountPayd":706.48,"Customer":81,"Year":2018,"Month":1,"Amount":322.03},{"AmountDue":383.78,"AmountPayd":824.03,"Customer":91,"Year":2018,"Month":6,"Amount":440.25},{"AmountDue":382.76,"AmountPayd":936.79,"Customer":29,"Year":2018,"Month":3,"Amount":554.03},{"AmountDue":381.10,"AmountPayd":968.77,"Customer":17,"Year":2018,"Month":8,"Amount":587.67},{"AmountDue":381.08,"AmountPayd":929.51,"Customer":50,"Year":2018,"Month":8,"Amount":548.43},{"AmountDue":377.66,"AmountPayd":763.87,"Customer":69,"Year":2018,"Month":12,"Amount":386.21},{"AmountDue":375.89,"AmountPayd":1289.32,"Customer":47,"Year":2018,"Month":2,"Amount":913.43},{"AmountDue":375.35,"AmountPayd":766.29,"Customer":91,"Year":2018,"Month":9,"Amount":390.94},{"AmountDue":372.74,"AmountPayd":562.59,"Customer":42,"Year":2018,"Month":8,"Amount":189.85},{"AmountDue":372.60,"AmountPayd":627.80,"Customer":17,"Year":2018,"Month":1,"Amount":255.20},{"AmountDue":372.35,"AmountPayd":847.11,"Customer":93,"Year":2018,"Month":12,"Amount":474.76},{"AmountDue":369.04,"AmountPayd":1318.10,"Customer":20,"Year":2018,"Month":9,"Amount":949.06},{"AmountDue":368.01,"AmountPayd":534.69,"Customer":77,"Year":2018,"Month":3,"Amount":166.68},{"AmountDue":367.29,"AmountPayd":676.59,"Customer":1,"Year":2018,"Month":11,"Amount":309.30},{"AmountDue":366.02,"AmountPayd":920.60,"Customer":9,"Year":2018,"Month":3,"Amount":554.58},{"AmountDue":365.74,"AmountPayd":912.00,"Customer":39,"Year":2018,"Month":7,"Amount":546.26},{"AmountDue":365.66,"AmountPayd":855.19,"Customer":71,"Year":2018,"Month":4,"Amount":489.53},{"AmountDue":365.31,"AmountPayd":1325.32,"Customer":26,"Year":2018,"Month":1,"Amount":960.01},{"AmountDue":363.71,"AmountPayd":1203.13,"Customer":33,"Year":2018,"Month":2,"Amount":839.42},{"AmountDue":362.57,"AmountPayd":796.47,"Customer":20,"Year":2018,"Month":11,"Amount":433.90},{"AmountDue":361.33,"AmountPayd":693.98,"Customer":3,"Year":2018,"Month":1,"Amount":332.65},{"AmountDue":360.15,"AmountPayd":1102.72,"Customer":32,"Year":2018,"Month":11,"Amount":742.57},{"AmountDue":359.34,"AmountPayd":1228.51,"Customer":26,"Year":2018,"Month":5,"Amount":869.17},{"AmountDue":359.28,"AmountPayd":825.55,"Customer":99,"Year":2018,"Month":8,"Amount":466.27},{"AmountDue":358.99,"AmountPayd":1197.34,"Customer":64,"Year":2018,"Month":12,"Amount":838.35},{"AmountDue":358.59,"AmountPayd":1049.03,"Customer":73,"Year":2018,"Month":12,"Amount":690.44},{"AmountDue":358.27,"AmountPayd":824.03,"Customer":91,"Year":2018,"Month":6,"Amount":465.76},{"AmountDue":357.54,"AmountPayd":1246.99,"Customer":100,"Year":2018,"Month":2,"Amount":889.45},{"AmountDue":357.07,"AmountPayd":1026.67,"Customer":7,"Year":2018,"Month":9,"Amount":669.60},{"AmountDue":355.23,"AmountPayd":774.90,"Customer":74,"Year":2018,"Month":2,"Amount":419.67},{"AmountDue":354.16,"AmountPayd":858.57,"Customer":90,"Year":2018,"Month":8,"Amount":504.41},{"AmountDue":353.38,"AmountPayd":1216.68,"Customer":35,"Year":2018,"Month":11,"Amount":863.30},{"AmountDue":352.94,"AmountPayd":1220.69,"Customer":29,"Year":2018,"Month":1,"Amount":867.75},{"AmountDue":352.13,"AmountPayd":747.47,"Customer":93,"Year":2018,"Month":1,"Amount":395.34},{"AmountDue":351.61,"AmountPayd":843.39,"Customer":34,"Year":2018,"Month":7,"Amount":491.78},{"AmountDue":350.91,"AmountPayd":1114.26,"Customer":19,"Year":2018,"Month":1,"Amount":763.35},{"AmountDue":350.54,"AmountPayd":888.49,"Customer":32,"Year":2018,"Month":6,"Amount":537.95},{"AmountDue":350.54,"AmountPayd":1400.37,"Customer":38,"Year":2018,"Month":3,"Amount":1049.83},{"AmountDue":350.12,"AmountPayd":975.10,"Customer":50,"Year":2018,"Month":3,"Amount":624.98},{"AmountDue":349.90,"AmountPayd":1237.71,"Customer":52,"Year":2018,"Month":3,"Amount":887.81},{"AmountDue":349.55,"AmountPayd":1214.22,"Customer":59,"Year":2018,"Month":4,"Amount":864.67},{"AmountDue":348.88,"AmountPayd":622.64,"Customer":23,"Year":2018,"Month":3,"Amount":273.76},{"AmountDue":348.43,"AmountPayd":540.95,"Customer":10,"Year":2018,"Month":7,"Amount":192.52},{"AmountDue":347.43,"AmountPayd":1078.82,"Customer":94,"Year":2018,"Month":3,"Amount":731.39},{"AmountDue":347.07,"AmountPayd":988.91,"Customer":39,"Year":2018,"Month":5,"Amount":641.84},{"AmountDue":344.77,"AmountPayd":704.10,"Customer":20,"Year":2018,"Month":12,"Amount":359.33},{"AmountDue":344.71,"AmountPayd":854.10,"Customer":11,"Year":2018,"Month":2,"Amount":509.39},{"AmountDue":344.36,"AmountPayd":661.85,"Customer":2,"Year":2018,"Month":5,"Amount":317.49},{"AmountDue":344.31,"AmountPayd":940.40,"Customer":49,"Year":2018,"Month":5,"Amount":596.09},{"AmountDue":341.68,"AmountPayd":611.10,"Customer":38,"Year":2018,"Month":5,"Amount":269.42},{"AmountDue":341.09,"AmountPayd":832.11,"Customer":93,"Year":2018,"Month":6,"Amount":491.02},{"AmountDue":338.89,"AmountPayd":1085.76,"Customer":61,"Year":2018,"Month":12,"Amount":746.87},{"AmountDue":337.07,"AmountPayd":907.94,"Customer":60,"Year":2018,"Month":10,"Amount":570.87},{"AmountDue":335.70,"AmountPayd":1021.88,"Customer":71,"Year":2018,"Month":12,"Amount":686.18},{"AmountDue":335.19,"AmountPayd":975.12,"Customer":100,"Year":2018,"Month":4,"Amount":639.93},{"AmountDue":333.73,"AmountPayd":972.82,"Customer":65,"Year":2018,"Month":11,"Amount":639.09},{"AmountDue":333.49,"AmountPayd":676.92,"Customer":92,"Year":2018,"Month":1,"Amount":343.43},{"AmountDue":332.73,"AmountPayd":981.79,"Customer":16,"Year":2018,"Month":8,"Amount":649.06},{"AmountDue":332.12,"AmountPayd":987.73,"Customer":88,"Year":2018,"Month":9,"Amount":655.61},{"AmountDue":328.65,"AmountPayd":792.85,"Customer":73,"Year":2018,"Month":3,"Amount":464.20},{"AmountDue":326.93,"AmountPayd":916.38,"Customer":71,"Year":2018,"Month":11,"Amount":589.45},{"AmountDue":325.85,"AmountPayd":774.90,"Customer":74,"Year":2018,"Month":2,"Amount":449.05},{"AmountDue":325.79,"AmountPayd":858.57,"Customer":90,"Year":2018,"Month":8,"Amount":532.78},{"AmountDue":325.58,"AmountPayd":950.56,"Customer":30,"Year":2018,"Month":2,"Amount":624.98},{"AmountDue":325.04,"AmountPayd":1102.10,"Customer":16,"Year":2018,"Month":3,"Amount":777.06},{"AmountDue":324.43,"AmountPayd":800.53,"Customer":16,"Year":2018,"Month":2,"Amount":476.10},{"AmountDue":323.92,"AmountPayd":1423.08,"Customer":14,"Year":2018,"Month":11,"Amount":1099.16},{"AmountDue":322.36,"AmountPayd":933.30,"Customer":45,"Year":2018,"Month":4,"Amount":610.94},{"AmountDue":322.34,"AmountPayd":805.90,"Customer":2,"Year":2018,"Month":3,"Amount":483.56},{"AmountDue":322.07,"AmountPayd":577.23,"Customer":8,"Year":2018,"Month":5,"Amount":255.16},{"AmountDue":320.64,"AmountPayd":774.66,"Customer":14,"Year":2018,"Month":3,"Amount":454.02},{"AmountDue":320.62,"AmountPayd":700.01,"Customer":31,"Year":2018,"Month":2,"Amount":379.39},{"AmountDue":320.32,"AmountPayd":1108.35,"Customer":6,"Year":2018,"Month":9,"Amount":788.03},{"AmountDue":318.84,"AmountPayd":510.66,"Customer":74,"Year":2018,"Month":8,"Amount":191.82},{"AmountDue":316.85,"AmountPayd":636.29,"Customer":67,"Year":2018,"Month":1,"Amount":319.44},{"AmountDue":313.42,"AmountPayd":1005.55,"Customer":55,"Year":2018,"Month":2,"Amount":692.13},{"AmountDue":309.30,"AmountPayd":699.62,"Customer":73,"Year":2018,"Month":1,"Amount":390.32},{"AmountDue":309.14,"AmountPayd":836.95,"Customer":77,"Year":2018,"Month":4,"Amount":527.81},{"AmountDue":307.10,"AmountPayd":1010.09,"Customer":28,"Year":2018,"Month":6,"Amount":702.99},{"AmountDue":304.75,"AmountPayd":1034.87,"Customer":52,"Year":2018,"Month":6,"Amount":730.12},{"AmountDue":303.41,"AmountPayd":1037.84,"Customer":72,"Year":2018,"Month":4,"Amount":734.43},{"AmountDue":302.27,"AmountPayd":973.89,"Customer":53,"Year":2018,"Month":4,"Amount":671.62},{"AmountDue":302.19,"AmountPayd":820.49,"Customer":8,"Year":2018,"Month":6,"Amount":518.30},{"AmountDue":300.97,"AmountPayd":930.78,"Customer":47,"Year":2018,"Month":10,"Amount":629.81},{"AmountDue":300.84,"AmountPayd":753.85,"Customer":2,"Year":2018,"Month":4,"Amount":453.01},{"AmountDue":300.44,"AmountPayd":1098.40,"Customer":78,"Year":2018,"Month":8,"Amount":797.96},{"AmountDue":299.82,"AmountPayd":1264.87,"Customer":62,"Year":2018,"Month":2,"Amount":965.05},{"AmountDue":299.70,"AmountPayd":1137.35,"Customer":20,"Year":2018,"Month":1,"Amount":837.65},{"AmountDue":296.95,"AmountPayd":911.75,"Customer":19,"Year":2018,"Month":2,"Amount":614.80},{"AmountDue":296.24,"AmountPayd":746.62,"Customer":4,"Year":2018,"Month":9,"Amount":450.38},{"AmountDue":295.64,"AmountPayd":467.84,"Customer":56,"Year":2018,"Month":1,"Amount":172.20},{"AmountDue":295.40,"AmountPayd":970.06,"Customer":30,"Year":2018,"Month":4,"Amount":674.66},{"AmountDue":293.02,"AmountPayd":879.14,"Customer":29,"Year":2018,"Month":9,"Amount":586.12},{"AmountDue":292.48,"AmountPayd":1090.24,"Customer":10,"Year":2018,"Month":3,"Amount":797.76},{"AmountDue":292.29,"AmountPayd":843.48,"Customer":77,"Year":2018,"Month":11,"Amount":551.19},{"AmountDue":291.84,"AmountPayd":811.80,"Customer":77,"Year":2018,"Month":8,"Amount":519.96},{"AmountDue":290.91,"AmountPayd":556.26,"Customer":78,"Year":2018,"Month":4,"Amount":265.35},{"AmountDue":290.02,"AmountPayd":963.75,"Customer":95,"Year":2018,"Month":12,"Amount":673.73},{"AmountDue":288.46,"AmountPayd":1120.10,"Customer":64,"Year":2018,"Month":4,"Amount":831.64},{"AmountDue":288.43,"AmountPayd":746.17,"Customer":64,"Year":2018,"Month":6,"Amount":457.74},{"AmountDue":287.90,"AmountPayd":738.04,"Customer":56,"Year":2018,"Month":5,"Amount":450.14},{"AmountDue":287.85,"AmountPayd":975.10,"Customer":50,"Year":2018,"Month":3,"Amount":687.25},{"AmountDue":286.38,"AmountPayd":554.92,"Customer":62,"Year":2018,"Month":7,"Amount":268.54},{"AmountDue":282.70,"AmountPayd":787.09,"Customer":96,"Year":2018,"Month":3,"Amount":504.39},{"AmountDue":282.69,"AmountPayd":933.30,"Customer":45,"Year":2018,"Month":4,"Amount":650.61},{"AmountDue":281.66,"AmountPayd":676.92,"Customer":92,"Year":2018,"Month":1,"Amount":395.26},{"AmountDue":278.99,"AmountPayd":1009.04,"Customer":28,"Year":2018,"Month":3,"Amount":730.05},{"AmountDue":277.22,"AmountPayd":1099.55,"Customer":34,"Year":2018,"Month":8,"Amount":822.33},{"AmountDue":277.14,"AmountPayd":555.07,"Customer":36,"Year":2018,"Month":2,"Amount":277.93},{"AmountDue":276.90,"AmountPayd":664.67,"Customer":68,"Year":2018,"Month":4,"Amount":387.77},{"AmountDue":275.41,"AmountPayd":1154.58,"Customer":1,"Year":2018,"Month":6,"Amount":879.17},{"AmountDue":274.10,"AmountPayd":1068.62,"Customer":28,"Year":2018,"Month":1,"Amount":794.52},{"AmountDue":273.76,"AmountPayd":622.64,"Customer":23,"Year":2018,"Month":3,"Amount":348.88},{"AmountDue":272.86,"AmountPayd":793.33,"Customer":90,"Year":2018,"Month":10,"Amount":520.47},{"AmountDue":270.37,"AmountPayd":575.88,"Customer":31,"Year":2018,"Month":3,"Amount":305.51},{"AmountDue":265.04,"AmountPayd":1021.60,"Customer":50,"Year":2018,"Month":7,"Amount":756.56},{"AmountDue":263.22,"AmountPayd":873.56,"Customer":56,"Year":2018,"Month":8,"Amount":610.34},{"AmountDue":262.43,"AmountPayd":834.79,"Customer":18,"Year":2018,"Month":10,"Amount":572.36},{"AmountDue":261.49,"AmountPayd":936.85,"Customer":100,"Year":2018,"Month":7,"Amount":675.36},{"AmountDue":260.30,"AmountPayd":920.60,"Customer":9,"Year":2018,"Month":3,"Amount":660.30},{"AmountDue":260.28,"AmountPayd":1021.60,"Customer":50,"Year":2018,"Month":7,"Amount":761.32},{"AmountDue":260.14,"AmountPayd":1085.14,"Customer":94,"Year":2018,"Month":6,"Amount":825.00},{"AmountDue":259.59,"AmountPayd":560.99,"Customer":92,"Year":2018,"Month":4,"Amount":301.40},{"AmountDue":259.35,"AmountPayd":843.48,"Customer":77,"Year":2018,"Month":11,"Amount":584.13},{"AmountDue":253.59,"AmountPayd":820.53,"Customer":16,"Year":2018,"Month":11,"Amount":566.94},{"AmountDue":252.48,"AmountPayd":554.92,"Customer":62,"Year":2018,"Month":7,"Amount":302.44},{"AmountDue":252.30,"AmountPayd":440.98,"Customer":79,"Year":2018,"Month":4,"Amount":188.68},{"AmountDue":251.18,"AmountPayd":901.29,"Customer":72,"Year":2018,"Month":7,"Amount":650.11},{"AmountDue":250.44,"AmountPayd":1202.07,"Customer":3,"Year":2018,"Month":4,"Amount":951.63},{"AmountDue":248.12,"AmountPayd":336.42,"Customer":74,"Year":2018,"Month":7,"Amount":88.30},{"AmountDue":246.50,"AmountPayd":525.64,"Customer":23,"Year":2018,"Month":11,"Amount":279.14},{"AmountDue":245.18,"AmountPayd":654.79,"Customer":90,"Year":2018,"Month":2,"Amount":409.61},{"AmountDue":244.04,"AmountPayd":823.65,"Customer":8,"Year":2018,"Month":1,"Amount":579.61},{"AmountDue":243.64,"AmountPayd":348.57,"Customer":24,"Year":2018,"Month":8,"Amount":104.93},{"AmountDue":243.09,"AmountPayd":440.69,"Customer":15,"Year":2018,"Month":9,"Amount":197.60},{"AmountDue":242.48,"AmountPayd":799.60,"Customer":37,"Year":2018,"Month":7,"Amount":557.12},{"AmountDue":242.39,"AmountPayd":743.10,"Customer":63,"Year":2018,"Month":1,"Amount":500.71},{"AmountDue":241.93,"AmountPayd":824.59,"Customer":86,"Year":2018,"Month":3,"Amount":582.66},{"AmountDue":241.25,"AmountPayd":824.59,"Customer":86,"Year":2018,"Month":3,"Amount":583.34},{"AmountDue":240.21,"AmountPayd":1160.65,"Customer":62,"Year":2018,"Month":6,"Amount":920.44},{"AmountDue":240.18,"AmountPayd":784.01,"Customer":79,"Year":2018,"Month":3,"Amount":543.83},{"AmountDue":238.55,"AmountPayd":831.38,"Customer":21,"Year":2018,"Month":2,"Amount":592.83},{"AmountDue":237.20,"AmountPayd":571.23,"Customer":3,"Year":2018,"Month":5,"Amount":334.03},{"AmountDue":236.19,"AmountPayd":690.64,"Customer":35,"Year":2018,"Month":10,"Amount":454.45},{"AmountDue":235.43,"AmountPayd":916.26,"Customer":42,"Year":2018,"Month":9,"Amount":680.83},{"AmountDue":235.27,"AmountPayd":688.09,"Customer":30,"Year":2018,"Month":8,"Amount":452.82},{"AmountDue":235.04,"AmountPayd":1083.70,"Customer":94,"Year":2018,"Month":11,"Amount":848.66},{"AmountDue":234.51,"AmountPayd":524.92,"Customer":83,"Year":2018,"Month":7,"Amount":290.41},{"AmountDue":231.59,"AmountPayd":1101.83,"Customer":40,"Year":2018,"Month":10,"Amount":870.24},{"AmountDue":230.63,"AmountPayd":495.32,"Customer":49,"Year":2018,"Month":10,"Amount":264.69},{"AmountDue":229.86,"AmountPayd":974.33,"Customer":48,"Year":2018,"Month":12,"Amount":744.47},{"AmountDue":229.69,"AmountPayd":737.96,"Customer":88,"Year":2018,"Month":6,"Amount":508.27},{"AmountDue":228.53,"AmountPayd":588.68,"Customer":53,"Year":2018,"Month":6,"Amount":360.15},{"AmountDue":227.95,"AmountPayd":1081.72,"Customer":51,"Year":2018,"Month":2,"Amount":853.77},{"AmountDue":225.14,"AmountPayd":706.48,"Customer":81,"Year":2018,"Month":1,"Amount":481.34},{"AmountDue":225.10,"AmountPayd":894.13,"Customer":23,"Year":2018,"Month":4,"Amount":669.03},{"AmountDue":224.50,"AmountPayd":609.10,"Customer":37,"Year":2018,"Month":5,"Amount":384.60},{"AmountDue":224.22,"AmountPayd":1089.20,"Customer":66,"Year":2018,"Month":7,"Amount":864.98},{"AmountDue":222.03,"AmountPayd":594.53,"Customer":51,"Year":2018,"Month":5,"Amount":372.50},{"AmountDue":220.28,"AmountPayd":742.91,"Customer":97,"Year":2018,"Month":3,"Amount":522.63},{"AmountDue":220.06,"AmountPayd":510.56,"Customer":53,"Year":2018,"Month":10,"Amount":290.50},{"AmountDue":217.82,"AmountPayd":673.05,"Customer":52,"Year":2018,"Month":11,"Amount":455.23},{"AmountDue":217.82,"AmountPayd":800.96,"Customer":59,"Year":2018,"Month":8,"Amount":583.14},{"AmountDue":216.71,"AmountPayd":442.34,"Customer":39,"Year":2018,"Month":10,"Amount":225.63},{"AmountDue":216.43,"AmountPayd":860.99,"Customer":86,"Year":2018,"Month":5,"Amount":644.56},{"AmountDue":215.78,"AmountPayd":591.55,"Customer":75,"Year":2018,"Month":8,"Amount":375.77},{"AmountDue":214.47,"AmountPayd":1070.91,"Customer":27,"Year":2018,"Month":3,"Amount":856.44},{"AmountDue":212.91,"AmountPayd":560.49,"Customer":80,"Year":2018,"Month":12,"Amount":347.58},{"AmountDue":212.43,"AmountPayd":789.44,"Customer":14,"Year":2018,"Month":12,"Amount":577.01},{"AmountDue":203.33,"AmountPayd":747.27,"Customer":73,"Year":2018,"Month":11,"Amount":543.94},{"AmountDue":202.94,"AmountPayd":619.67,"Customer":58,"Year":2018,"Month":1,"Amount":416.73},{"AmountDue":200.02,"AmountPayd":961.77,"Customer":80,"Year":2018,"Month":10,"Amount":761.75},{"AmountDue":194.86,"AmountPayd":793.33,"Customer":90,"Year":2018,"Month":10,"Amount":598.47},{"AmountDue":191.90,"AmountPayd":1026.46,"Customer":23,"Year":2018,"Month":7,"Amount":834.56},{"AmountDue":191.63,"AmountPayd":485.11,"Customer":16,"Year":2018,"Month":4,"Amount":293.48},{"AmountDue":191.46,"AmountPayd":413.62,"Customer":69,"Year":2018,"Month":4,"Amount":222.16},{"AmountDue":190.67,"AmountPayd":705.78,"Customer":95,"Year":2018,"Month":5,"Amount":515.11},{"AmountDue":190.39,"AmountPayd":896.99,"Customer":17,"Year":2018,"Month":6,"Amount":706.60},{"AmountDue":190.13,"AmountPayd":1084.20,"Customer":29,"Year":2018,"Month":6,"Amount":894.07},{"AmountDue":188.96,"AmountPayd":502.57,"Customer":27,"Year":2018,"Month":7,"Amount":313.61},{"AmountDue":187.50,"AmountPayd":606.83,"Customer":57,"Year":2018,"Month":7,"Amount":419.33},{"AmountDue":186.52,"AmountPayd":792.93,"Customer":29,"Year":2018,"Month":7,"Amount":606.41},{"AmountDue":185.85,"AmountPayd":652.12,"Customer":51,"Year":2018,"Month":10,"Amount":466.27},{"AmountDue":184.75,"AmountPayd":513.96,"Customer":86,"Year":2018,"Month":1,"Amount":329.21},{"AmountDue":181.61,"AmountPayd":413.62,"Customer":69,"Year":2018,"Month":4,"Amount":232.01},{"AmountDue":181.60,"AmountPayd":541.13,"Customer":14,"Year":2018,"Month":1,"Amount":359.53},{"AmountDue":181.44,"AmountPayd":583.40,"Customer":87,"Year":2018,"Month":1,"Amount":401.96},{"AmountDue":181.26,"AmountPayd":795.28,"Customer":82,"Year":2018,"Month":6,"Amount":614.02},{"AmountDue":181.18,"AmountPayd":797.11,"Customer":97,"Year":2018,"Month":10,"Amount":615.93},{"AmountDue":179.34,"AmountPayd":964.45,"Customer":7,"Year":2018,"Month":11,"Amount":785.11},{"AmountDue":178.89,"AmountPayd":807.33,"Customer":67,"Year":2018,"Month":5,"Amount":628.44},{"AmountDue":178.31,"AmountPayd":388.44,"Customer":32,"Year":2018,"Month":2,"Amount":210.13},{"AmountDue":177.78,"AmountPayd":562.59,"Customer":42,"Year":2018,"Month":8,"Amount":384.81},{"AmountDue":174.48,"AmountPayd":1058.85,"Customer":73,"Year":2018,"Month":8,"Amount":884.37},{"AmountDue":174.30,"AmountPayd":605.00,"Customer":13,"Year":2018,"Month":1,"Amount":430.70},{"AmountDue":172.43,"AmountPayd":808.38,"Customer":52,"Year":2018,"Month":4,"Amount":635.95},{"AmountDue":170.25,"AmountPayd":533.30,"Customer":24,"Year":2018,"Month":11,"Amount":363.05},{"AmountDue":169.21,"AmountPayd":800.79,"Customer":9,"Year":2018,"Month":11,"Amount":631.58},{"AmountDue":168.27,"AmountPayd":774.66,"Customer":14,"Year":2018,"Month":3,"Amount":606.39},{"AmountDue":167.42,"AmountPayd":355.26,"Customer":17,"Year":2018,"Month":2,"Amount":187.84},{"AmountDue":167.40,"AmountPayd":611.59,"Customer":39,"Year":2018,"Month":3,"Amount":444.19},{"AmountDue":166.94,"AmountPayd":1000.95,"Customer":75,"Year":2018,"Month":1,"Amount":834.01},{"AmountDue":166.78,"AmountPayd":788.03,"Customer":65,"Year":2018,"Month":8,"Amount":621.25},{"AmountDue":165.81,"AmountPayd":789.37,"Customer":37,"Year":2018,"Month":9,"Amount":623.56},{"AmountDue":164.76,"AmountPayd":800.98,"Customer":11,"Year":2018,"Month":5,"Amount":636.22},{"AmountDue":163.56,"AmountPayd":669.68,"Customer":66,"Year":2018,"Month":12,"Amount":506.12},{"AmountDue":162.10,"AmountPayd":697.77,"Customer":35,"Year":2018,"Month":1,"Amount":535.67},{"AmountDue":161.19,"AmountPayd":1149.21,"Customer":19,"Year":2018,"Month":10,"Amount":988.02},{"AmountDue":159.11,"AmountPayd":938.24,"Customer":34,"Year":2018,"Month":11,"Amount":779.13},{"AmountDue":158.95,"AmountPayd":959.49,"Customer":35,"Year":2018,"Month":12,"Amount":800.54},{"AmountDue":158.05,"AmountPayd":458.28,"Customer":75,"Year":2018,"Month":12,"Amount":300.23},{"AmountDue":155.98,"AmountPayd":428.12,"Customer":8,"Year":2018,"Month":2,"Amount":272.14},{"AmountDue":155.88,"AmountPayd":636.29,"Customer":67,"Year":2018,"Month":1,"Amount":480.41},{"AmountDue":155.53,"AmountPayd":577.12,"Customer":45,"Year":2018,"Month":9,"Amount":421.59},{"AmountDue":155.20,"AmountPayd":560.99,"Customer":92,"Year":2018,"Month":4,"Amount":405.79},{"AmountDue":154.90,"AmountPayd":792.85,"Customer":73,"Year":2018,"Month":3,"Amount":637.95},{"AmountDue":154.00,"AmountPayd":1238.18,"Customer":74,"Year":2018,"Month":10,"Amount":1084.18},{"AmountDue":153.16,"AmountPayd":763.43,"Customer":36,"Year":2018,"Month":12,"Amount":610.27},{"AmountDue":151.82,"AmountPayd":748.89,"Customer":51,"Year":2018,"Month":1,"Amount":597.07},{"AmountDue":151.33,"AmountPayd":709.46,"Customer":17,"Year":2018,"Month":5,"Amount":558.13},{"AmountDue":151.28,"AmountPayd":1053.52,"Customer":24,"Year":2018,"Month":4,"Amount":902.24},{"AmountDue":150.88,"AmountPayd":459.27,"Customer":11,"Year":2018,"Month":11,"Amount":308.39},{"AmountDue":150.36,"AmountPayd":810.60,"Customer":85,"Year":2018,"Month":6,"Amount":660.24},{"AmountDue":147.87,"AmountPayd":388.44,"Customer":32,"Year":2018,"Month":2,"Amount":240.57},{"AmountDue":146.37,"AmountPayd":644.84,"Customer":99,"Year":2018,"Month":6,"Amount":498.47},{"AmountDue":145.58,"AmountPayd":856.26,"Customer":60,"Year":2018,"Month":9,"Amount":710.68},{"AmountDue":144.44,"AmountPayd":1042.71,"Customer":33,"Year":2018,"Month":3,"Amount":898.27},{"AmountDue":143.14,"AmountPayd":579.55,"Customer":15,"Year":2018,"Month":6,"Amount":436.41},{"AmountDue":140.37,"AmountPayd":862.33,"Customer":89,"Year":2018,"Month":8,"Amount":721.96},{"AmountDue":139.74,"AmountPayd":624.76,"Customer":74,"Year":2018,"Month":11,"Amount":485.02},{"AmountDue":139.53,"AmountPayd":621.05,"Customer":67,"Year":2018,"Month":3,"Amount":481.52},{"AmountDue":138.97,"AmountPayd":888.54,"Customer":7,"Year":2018,"Month":8,"Amount":749.57},{"AmountDue":137.12,"AmountPayd":629.14,"Customer":30,"Year":2018,"Month":11,"Amount":492.02},{"AmountDue":135.57,"AmountPayd":627.21,"Customer":74,"Year":2018,"Month":5,"Amount":491.64},{"AmountDue":135.28,"AmountPayd":702.08,"Customer":25,"Year":2018,"Month":9,"Amount":566.80},{"AmountDue":134.92,"AmountPayd":664.67,"Customer":68,"Year":2018,"Month":4,"Amount":529.75},{"AmountDue":134.37,"AmountPayd":359.09,"Customer":61,"Year":2018,"Month":10,"Amount":224.72},{"AmountDue":134.18,"AmountPayd":740.95,"Customer":6,"Year":2018,"Month":12,"Amount":606.77},{"AmountDue":133.78,"AmountPayd":387.94,"Customer":12,"Year":2018,"Month":6,"Amount":254.16},{"AmountDue":133.48,"AmountPayd":820.49,"Customer":8,"Year":2018,"Month":6,"Amount":687.01},{"AmountDue":133.11,"AmountPayd":611.68,"Customer":89,"Year":2018,"Month":7,"Amount":478.57},{"AmountDue":133.07,"AmountPayd":254.83,"Customer":90,"Year":2018,"Month":5,"Amount":121.76},{"AmountDue":132.75,"AmountPayd":1039.16,"Customer":35,"Year":2018,"Month":4,"Amount":906.41},{"AmountDue":131.60,"AmountPayd":734.72,"Customer":31,"Year":2018,"Month":7,"Amount":603.12},{"AmountDue":130.16,"AmountPayd":800.79,"Customer":9,"Year":2018,"Month":11,"Amount":670.63},{"AmountDue":129.87,"AmountPayd":430.81,"Customer":24,"Year":2018,"Month":12,"Amount":300.94},{"AmountDue":127.14,"AmountPayd":591.54,"Customer":31,"Year":2018,"Month":6,"Amount":464.40},{"AmountDue":125.17,"AmountPayd":935.27,"Customer":36,"Year":2018,"Month":4,"Amount":810.10},{"AmountDue":124.69,"AmountPayd":435.35,"Customer":1,"Year":2018,"Month":7,"Amount":310.66},{"AmountDue":123.48,"AmountPayd":622.62,"Customer":56,"Year":2018,"Month":9,"Amount":499.14},{"AmountDue":118.72,"AmountPayd":1154.04,"Customer":18,"Year":2018,"Month":3,"Amount":1035.32},{"AmountDue":118.44,"AmountPayd":637.86,"Customer":82,"Year":2018,"Month":8,"Amount":519.42},{"AmountDue":116.70,"AmountPayd":218.38,"Customer":2,"Year":2018,"Month":7,"Amount":101.68},{"AmountDue":114.62,"AmountPayd":747.47,"Customer":93,"Year":2018,"Month":1,"Amount":632.85},{"AmountDue":114.17,"AmountPayd":599.57,"Customer":12,"Year":2018,"Month":11,"Amount":485.40},{"AmountDue":113.87,"AmountPayd":1161.31,"Customer":85,"Year":2018,"Month":12,"Amount":1047.44},{"AmountDue":113.18,"AmountPayd":624.10,"Customer":100,"Year":2018,"Month":3,"Amount":510.92},{"AmountDue":112.69,"AmountPayd":788.76,"Customer":90,"Year":2018,"Month":1,"Amount":676.07},{"AmountDue":109.57,"AmountPayd":355.26,"Customer":17,"Year":2018,"Month":2,"Amount":245.69},{"AmountDue":109.22,"AmountPayd":1018.62,"Customer":13,"Year":2018,"Month":10,"Amount":909.40},{"AmountDue":106.50,"AmountPayd":792.09,"Customer":49,"Year":2018,"Month":11,"Amount":685.59},{"AmountDue":105.64,"AmountPayd":608.81,"Customer":9,"Year":2018,"Month":8,"Amount":503.17},{"AmountDue":104.15,"AmountPayd":949.83,"Customer":13,"Year":2018,"Month":12,"Amount":845.68},{"AmountDue":98.53,"AmountPayd":704.10,"Customer":20,"Year":2018,"Month":12,"Amount":605.57},{"AmountDue":97.91,"AmountPayd":209.67,"Customer":32,"Year":2018,"Month":9,"Amount":111.76},{"AmountDue":97.45,"AmountPayd":837.28,"Customer":83,"Year":2018,"Month":2,"Amount":739.83},{"AmountDue":96.24,"AmountPayd":1226.16,"Customer":79,"Year":2018,"Month":9,"Amount":1129.92},{"AmountDue":95.90,"AmountPayd":976.20,"Customer":19,"Year":2018,"Month":12,"Amount":880.30},{"AmountDue":94.72,"AmountPayd":788.03,"Customer":65,"Year":2018,"Month":8,"Amount":693.31},{"AmountDue":94.69,"AmountPayd":548.22,"Customer":22,"Year":2018,"Month":5,"Amount":453.53},{"AmountDue":94.20,"AmountPayd":986.89,"Customer":79,"Year":2018,"Month":6,"Amount":892.69},{"AmountDue":92.48,"AmountPayd":289.37,"Customer":33,"Year":2018,"Month":10,"Amount":196.89},{"AmountDue":88.38,"AmountPayd":686.65,"Customer":87,"Year":2018,"Month":2,"Amount":598.27},{"AmountDue":85.65,"AmountPayd":501.77,"Customer":2,"Year":2018,"Month":2,"Amount":416.12},{"AmountDue":84.48,"AmountPayd":499.49,"Customer":31,"Year":2018,"Month":5,"Amount":415.01},{"AmountDue":83.59,"AmountPayd":571.23,"Customer":3,"Year":2018,"Month":5,"Amount":487.64},{"AmountDue":82.36,"AmountPayd":599.57,"Customer":12,"Year":2018,"Month":11,"Amount":517.21},{"AmountDue":79.95,"AmountPayd":824.54,"Customer":88,"Year":2018,"Month":4,"Amount":744.59},{"AmountDue":79.91,"AmountPayd":577.12,"Customer":45,"Year":2018,"Month":9,"Amount":497.21},{"AmountDue":79.26,"AmountPayd":888.60,"Customer":66,"Year":2018,"Month":6,"Amount":809.34},{"AmountDue":78.55,"AmountPayd":555.57,"Customer":34,"Year":2018,"Month":4,"Amount":477.02},{"AmountDue":77.87,"AmountPayd":348.57,"Customer":24,"Year":2018,"Month":8,"Amount":270.70},{"AmountDue":75.54,"AmountPayd":430.81,"Customer":24,"Year":2018,"Month":12,"Amount":355.27},{"AmountDue":72.99,"AmountPayd":649.10,"Customer":8,"Year":2018,"Month":3,"Amount":576.11},{"AmountDue":72.69,"AmountPayd":123.99,"Customer":1,"Year":2018,"Month":1,"Amount":51.30},{"AmountDue":72.42,"AmountPayd":705.78,"Customer":95,"Year":2018,"Month":5,"Amount":633.36},{"AmountDue":71.64,"AmountPayd":636.37,"Customer":63,"Year":2018,"Month":8,"Amount":564.73},{"AmountDue":71.36,"AmountPayd":1014.43,"Customer":96,"Year":2018,"Month":4,"Amount":943.07},{"AmountDue":69.66,"AmountPayd":718.31,"Customer":66,"Year":2018,"Month":10,"Amount":648.65},{"AmountDue":69.45,"AmountPayd":289.37,"Customer":33,"Year":2018,"Month":10,"Amount":219.92},{"AmountDue":69.38,"AmountPayd":934.32,"Customer":3,"Year":2018,"Month":8,"Amount":864.94},{"AmountDue":67.70,"AmountPayd":516.00,"Customer":7,"Year":2018,"Month":5,"Amount":448.30},{"AmountDue":66.73,"AmountPayd":801.86,"Customer":71,"Year":2018,"Month":2,"Amount":735.13},{"AmountDue":63.63,"AmountPayd":749.62,"Customer":81,"Year":2018,"Month":12,"Amount":685.99},{"AmountDue":63.28,"AmountPayd":643.19,"Customer":64,"Year":2018,"Month":1,"Amount":579.91},{"AmountDue":62.75,"AmountPayd":299.05,"Customer":8,"Year":2018,"Month":4,"Amount":236.30},{"AmountDue":62.54,"AmountPayd":837.86,"Customer":4,"Year":2018,"Month":8,"Amount":775.32},{"AmountDue":62.54,"AmountPayd":737.96,"Customer":88,"Year":2018,"Month":6,"Amount":675.42},{"AmountDue":61.77,"AmountPayd":360.97,"Customer":91,"Year":2018,"Month":12,"Amount":299.20},{"AmountDue":61.44,"AmountPayd":823.65,"Customer":8,"Year":2018,"Month":1,"Amount":762.21},{"AmountDue":61.32,"AmountPayd":917.37,"Customer":29,"Year":2018,"Month":4,"Amount":856.05},{"AmountDue":58.60,"AmountPayd":186.98,"Customer":82,"Year":2018,"Month":7,"Amount":128.38},{"AmountDue":57.79,"AmountPayd":349.91,"Customer":28,"Year":2018,"Month":12,"Amount":292.12},{"AmountDue":54.62,"AmountPayd":700.01,"Customer":31,"Year":2018,"Month":2,"Amount":645.39},{"AmountDue":51.30,"AmountPayd":123.99,"Customer":1,"Year":2018,"Month":1,"Amount":72.69},{"AmountDue":51.26,"AmountPayd":728.33,"Customer":6,"Year":2018,"Month":4,"Amount":677.07},{"AmountDue":48.31,"AmountPayd":297.62,"Customer":36,"Year":2018,"Month":10,"Amount":249.31},{"AmountDue":47.02,"AmountPayd":913.38,"Customer":68,"Year":2018,"Month":12,"Amount":866.36},{"AmountDue":46.69,"AmountPayd":776.22,"Customer":29,"Year":2018,"Month":10,"Amount":729.53},{"AmountDue":45.82,"AmountPayd":168.71,"Customer":69,"Year":2018,"Month":1,"Amount":122.89},{"AmountDue":43.34,"AmountPayd":439.22,"Customer":4,"Year":2018,"Month":1,"Amount":395.88},{"AmountDue":43.34,"AmountPayd":717.07,"Customer":14,"Year":2018,"Month":10,"Amount":673.73},{"AmountDue":43.34,"AmountPayd":534.69,"Customer":77,"Year":2018,"Month":3,"Amount":491.35},{"AmountDue":42.99,"AmountPayd":164.14,"Customer":57,"Year":2018,"Month":12,"Amount":121.15},{"AmountDue":41.78,"AmountPayd":833.31,"Customer":67,"Year":2018,"Month":10,"Amount":791.53},{"AmountDue":41.03,"AmountPayd":922.47,"Customer":53,"Year":2018,"Month":8,"Amount":881.44},{"AmountDue":39.86,"AmountPayd":254.35,"Customer":46,"Year":2018,"Month":4,"Amount":214.49},{"AmountDue":39.56,"AmountPayd":621.05,"Customer":67,"Year":2018,"Month":3,"Amount":581.49},{"AmountDue":37.97,"AmountPayd":629.14,"Customer":30,"Year":2018,"Month":11,"Amount":591.17},{"AmountDue":37.91,"AmountPayd":972.82,"Customer":65,"Year":2018,"Month":11,"Amount":934.91},{"AmountDue":36.94,"AmountPayd":402.82,"Customer":96,"Year":2018,"Month":2,"Amount":365.88},{"AmountDue":35.94,"AmountPayd":548.22,"Customer":22,"Year":2018,"Month":5,"Amount":512.28},{"AmountDue":35.53,"AmountPayd":527.78,"Customer":73,"Year":2018,"Month":9,"Amount":492.25},{"AmountDue":34.86,"AmountPayd":507.17,"Customer":31,"Year":2018,"Month":12,"Amount":472.31},{"AmountDue":33.66,"AmountPayd":611.26,"Customer":87,"Year":2018,"Month":7,"Amount":577.60},{"AmountDue":31.78,"AmountPayd":413.11,"Customer":46,"Year":2018,"Month":5,"Amount":381.33},{"AmountDue":30.62,"AmountPayd":805.90,"Customer":2,"Year":2018,"Month":3,"Amount":775.28},{"AmountDue":29.18,"AmountPayd":529.20,"Customer":46,"Year":2018,"Month":2,"Amount":500.02},{"AmountDue":28.75,"AmountPayd":920.44,"Customer":36,"Year":2018,"Month":8,"Amount":891.69},{"AmountDue":28.24,"AmountPayd":864.30,"Customer":81,"Year":2018,"Month":10,"Amount":836.06},{"AmountDue":27.40,"AmountPayd":281.98,"Customer":32,"Year":2018,"Month":1,"Amount":254.58},{"AmountDue":25.84,"AmountPayd":294.65,"Customer":97,"Year":2018,"Month":2,"Amount":268.81},{"AmountDue":25.47,"AmountPayd":467.84,"Customer":56,"Year":2018,"Month":1,"Amount":442.37},{"AmountDue":23.89,"AmountPayd":435.62,"Customer":5,"Year":2018,"Month":11,"Amount":411.73},{"AmountDue":21.20,"AmountPayd":685.38,"Customer":4,"Year":2018,"Month":4,"Amount":664.18},{"AmountDue":20.14,"AmountPayd":155.41,"Customer":11,"Year":2018,"Month":1,"Amount":135.27},{"AmountDue":17.29,"AmountPayd":348.27,"Customer":85,"Year":2018,"Month":5,"Amount":330.98},{"AmountDue":16.92,"AmountPayd":465.65,"Customer":99,"Year":2018,"Month":3,"Amount":448.73},{"AmountDue":16.65,"AmountPayd":661.85,"Customer":2,"Year":2018,"Month":5,"Amount":645.20},{"AmountDue":15.59,"AmountPayd":594.22,"Customer":24,"Year":2018,"Month":10,"Amount":578.63},{"AmountDue":13.04,"AmountPayd":875.34,"Customer":33,"Year":2018,"Month":7,"Amount":862.30},{"AmountDue":10.97,"AmountPayd":453.42,"Customer":93,"Year":2018,"Month":9,"Amount":442.45},{"AmountDue":7.98,"AmountPayd":774.68,"Customer":28,"Year":2018,"Month":5,"Amount":766.70},{"AmountDue":7.96,"AmountPayd":616.58,"Customer":54,"Year":2018,"Month":9,"Amount":608.62},{"AmountDue":7.87,"AmountPayd":650.97,"Customer":88,"Year":2018,"Month":3,"Amount":643.10},{"AmountDue":6.26,"AmountPayd":441.91,"Customer":71,"Year":2018,"Month":3,"Amount":435.65},{"AmountDue":5.69,"AmountPayd":796.74,"Customer":58,"Year":2018,"Month":5,"Amount":791.05},{"AmountDue":5.60,"AmountPayd":749.83,"Customer":26,"Year":2018,"Month":3,"Amount":744.23},{"AmountDue":5.60,"AmountPayd":703.74,"Customer":74,"Year":2018,"Month":6,"Amount":698.14},{"AmountDue":2.36,"AmountPayd":759.56,"Customer":84,"Year":2018,"Month":1,"Amount":757.20},{"AmountDue":-5.14,"AmountPayd":303.39,"Customer":77,"Year":2018,"Month":2,"Amount":308.53},{"AmountDue":-5.60,"AmountPayd":550.49,"Customer":26,"Year":2018,"Month":4,"Amount":556.09},{"AmountDue":-6.17,"AmountPayd":622.62,"Customer":56,"Year":2018,"Month":9,"Amount":628.79},{"AmountDue":-8.67,"AmountPayd":1110.75,"Customer":54,"Year":2018,"Month":8,"Amount":1119.42},{"AmountDue":-9.32,"AmountPayd":142.26,"Customer":62,"Year":2018,"Month":8,"Amount":151.58},{"AmountDue":-10.31,"AmountPayd":486.52,"Customer":62,"Year":2018,"Month":12,"Amount":496.83},{"AmountDue":-10.35,"AmountPayd":441.19,"Customer":82,"Year":2018,"Month":1,"Amount":451.54},{"AmountDue":-10.94,"AmountPayd":331.71,"Customer":13,"Year":2018,"Month":2,"Amount":342.65},{"AmountDue":-14.87,"AmountPayd":619.15,"Customer":41,"Year":2018,"Month":2,"Amount":634.02},{"AmountDue":-17.20,"AmountPayd":699.24,"Customer":4,"Year":2018,"Month":11,"Amount":716.44},{"AmountDue":-22.75,"AmountPayd":568.66,"Customer":32,"Year":2018,"Month":10,"Amount":591.41},{"AmountDue":-22.86,"AmountPayd":853.63,"Customer":51,"Year":2018,"Month":6,"Amount":876.49},{"AmountDue":-27.26,"AmountPayd":652.12,"Customer":51,"Year":2018,"Month":10,"Amount":679.38},{"AmountDue":-29.82,"AmountPayd":179.88,"Customer":100,"Year":2018,"Month":1,"Amount":209.70},{"AmountDue":-31.23,"AmountPayd":1078.01,"Customer":54,"Year":2018,"Month":2,"Amount":1109.24},{"AmountDue":-31.56,"AmountPayd":485.11,"Customer":16,"Year":2018,"Month":4,"Amount":516.67},{"AmountDue":-33.67,"AmountPayd":175.19,"Customer":95,"Year":2018,"Month":11,"Amount":208.86},{"AmountDue":-35.49,"AmountPayd":786.22,"Customer":22,"Year":2018,"Month":3,"Amount":821.71},{"AmountDue":-35.53,"AmountPayd":34.86,"Customer":73,"Year":2018,"Month":10,"Amount":70.39},{"AmountDue":-36.30,"AmountPayd":230.92,"Customer":13,"Year":2018,"Month":6,"Amount":267.22},{"AmountDue":-36.87,"AmountPayd":463.70,"Customer":9,"Year":2018,"Month":4,"Amount":500.57},{"AmountDue":-39.42,"AmountPayd":553.13,"Customer":5,"Year":2018,"Month":12,"Amount":592.55},{"AmountDue":-43.43,"AmountPayd":839.40,"Customer":53,"Year":2018,"Month":5,"Amount":882.83},{"AmountDue":-43.53,"AmountPayd":948.14,"Customer":100,"Year":2018,"Month":9,"Amount":991.67},{"AmountDue":-46.18,"AmountPayd":910.40,"Customer":66,"Year":2018,"Month":5,"Amount":956.58},{"AmountDue":-48.19,"AmountPayd":445.87,"Customer":41,"Year":2018,"Month":12,"Amount":494.06},{"AmountDue":-49.79,"AmountPayd":498.14,"Customer":68,"Year":2018,"Month":11,"Amount":547.93},{"AmountDue":-50.78,"AmountPayd":104.33,"Customer":88,"Year":2018,"Month":12,"Amount":155.11},{"AmountDue":-53.93,"AmountPayd":208.97,"Customer":72,"Year":2018,"Month":1,"Amount":262.90},{"AmountDue":-54.94,"AmountPayd":1024.60,"Customer":60,"Year":2018,"Month":12,"Amount":1079.54},{"AmountDue":-55.87,"AmountPayd":166.43,"Customer":60,"Year":2018,"Month":3,"Amount":222.30},{"AmountDue":-55.94,"AmountPayd":347.18,"Customer":11,"Year":2018,"Month":9,"Amount":403.12},{"AmountDue":-58.22,"AmountPayd":439.22,"Customer":4,"Year":2018,"Month":1,"Amount":497.44},{"AmountDue":-61.01,"AmountPayd":701.98,"Customer":30,"Year":2018,"Month":3,"Amount":762.99},{"AmountDue":-61.90,"AmountPayd":510.66,"Customer":74,"Year":2018,"Month":8,"Amount":572.56},{"AmountDue":-62.54,"AmountPayd":168.43,"Customer":7,"Year":2018,"Month":1,"Amount":230.97},{"AmountDue":-65.40,"AmountPayd":297.58,"Customer":97,"Year":2018,"Month":9,"Amount":362.98},{"AmountDue":-66.98,"AmountPayd":538.74,"Customer":54,"Year":2018,"Month":12,"Amount":605.72},{"AmountDue":-67.70,"AmountPayd":131.62,"Customer":7,"Year":2018,"Month":6,"Amount":199.32},{"AmountDue":-68.08,"AmountPayd":627.80,"Customer":17,"Year":2018,"Month":1,"Amount":695.88},{"AmountDue":-69.38,"AmountPayd":63.28,"Customer":3,"Year":2018,"Month":9,"Amount":132.66},{"AmountDue":-69.66,"AmountPayd":332.14,"Customer":66,"Year":2018,"Month":11,"Amount":401.80},{"AmountDue":-71.36,"AmountPayd":512.49,"Customer":96,"Year":2018,"Month":5,"Amount":583.85},{"AmountDue":-71.64,"AmountPayd":237.89,"Customer":46,"Year":2018,"Month":6,"Amount":309.53},{"AmountDue":-77.48,"AmountPayd":143.62,"Customer":10,"Year":2018,"Month":6,"Amount":221.10},{"AmountDue":-81.37,"AmountPayd":142.78,"Customer":48,"Year":2018,"Month":6,"Amount":224.15},{"AmountDue":-89.80,"AmountPayd":611.10,"Customer":38,"Year":2018,"Month":5,"Amount":700.90},{"AmountDue":-101.36,"AmountPayd":239.72,"Customer":37,"Year":2018,"Month":8,"Amount":341.08},{"AmountDue":-101.45,"AmountPayd":369.11,"Customer":59,"Year":2018,"Month":3,"Amount":470.56},{"AmountDue":-104.91,"AmountPayd":387.94,"Customer":12,"Year":2018,"Month":6,"Amount":492.85},{"AmountDue":-111.25,"AmountPayd":297.62,"Customer":36,"Year":2018,"Month":10,"Amount":408.87},{"AmountDue":-111.41,"AmountPayd":101.31,"Customer":41,"Year":2018,"Month":4,"Amount":212.72},{"AmountDue":-112.12,"AmountPayd":294.68,"Customer":94,"Year":2018,"Month":8,"Amount":406.80},{"AmountDue":-116.02,"AmountPayd":568.74,"Customer":81,"Year":2018,"Month":2,"Amount":684.76},{"AmountDue":-116.97,"AmountPayd":241.22,"Customer":65,"Year":2018,"Month":6,"Amount":358.19},{"AmountDue":-121.97,"AmountPayd":440.69,"Customer":15,"Year":2018,"Month":9,"Amount":562.66},{"AmountDue":-126.14,"AmountPayd":384.56,"Customer":51,"Year":2018,"Month":7,"Amount":510.70},{"AmountDue":-129.75,"AmountPayd":733.01,"Customer":63,"Year":2018,"Month":2,"Amount":862.76},{"AmountDue":-130.64,"AmountPayd":608.40,"Customer":94,"Year":2018,"Month":2,"Amount":739.04},{"AmountDue":-130.81,"AmountPayd":609.67,"Customer":30,"Year":2018,"Month":5,"Amount":740.48},{"AmountDue":-131.46,"AmountPayd":319.47,"Customer":45,"Year":2018,"Month":10,"Amount":450.93},{"AmountDue":-138.69,"AmountPayd":209.43,"Customer":31,"Year":2018,"Month":10,"Amount":348.12},{"AmountDue":-139.66,"AmountPayd":279.43,"Customer":59,"Year":2018,"Month":6,"Amount":419.09},{"AmountDue":-141.61,"AmountPayd":325.31,"Customer":1,"Year":2018,"Month":8,"Amount":466.92},{"AmountDue":-142.91,"AmountPayd":46.03,"Customer":15,"Year":2018,"Month":10,"Amount":188.94},{"AmountDue":-143.91,"AmountPayd":382.28,"Customer":47,"Year":2018,"Month":7,"Amount":526.19},{"AmountDue":-146.50,"AmountPayd":215.20,"Customer":42,"Year":2018,"Month":1,"Amount":361.70},{"AmountDue":-147.51,"AmountPayd":611.59,"Customer":39,"Year":2018,"Month":3,"Amount":759.10},{"AmountDue":-150.90,"AmountPayd":689.68,"Customer":43,"Year":2018,"Month":5,"Amount":840.58},{"AmountDue":-151.28,"AmountPayd":145.05,"Customer":24,"Year":2018,"Month":5,"Amount":296.33},{"AmountDue":-152.74,"AmountPayd":455.93,"Customer":76,"Year":2018,"Month":3,"Amount":608.67},{"AmountDue":-153.49,"AmountPayd":193.42,"Customer":63,"Year":2018,"Month":10,"Amount":346.91},{"AmountDue":-158.05,"AmountPayd":176.63,"Customer":76,"Year":2018,"Month":1,"Amount":334.68},{"AmountDue":-158.95,"AmountPayd":240.27,"Customer":36,"Year":2018,"Month":1,"Amount":399.22},{"AmountDue":-159.41,"AmountPayd":789.01,"Customer":76,"Year":2018,"Month":12,"Amount":948.42},{"AmountDue":-161.19,"AmountPayd":112.18,"Customer":19,"Year":2018,"Month":11,"Amount":273.37},{"AmountDue":-162.51,"AmountPayd":158.26,"Customer":17,"Year":2018,"Month":10,"Amount":320.77},{"AmountDue":-163.29,"AmountPayd":351.00,"Customer":99,"Year":2018,"Month":7,"Amount":514.29},{"AmountDue":-163.36,"AmountPayd":373.55,"Customer":13,"Year":2018,"Month":3,"Amount":536.91},{"AmountDue":-166.18,"AmountPayd":441.63,"Customer":78,"Year":2018,"Month":7,"Amount":607.81},{"AmountDue":-166.83,"AmountPayd":80.23,"Customer":31,"Year":2018,"Month":11,"Amount":247.06},{"AmountDue":-171.76,"AmountPayd":719.64,"Customer":8,"Year":2018,"Month":11,"Amount":891.40},{"AmountDue":-172.55,"AmountPayd":623.70,"Customer":93,"Year":2018,"Month":8,"Amount":796.25},{"AmountDue":-173.65,"AmountPayd":63.11,"Customer":40,"Year":2018,"Month":5,"Amount":236.76},{"AmountDue":-175.55,"AmountPayd":473.76,"Customer":34,"Year":2018,"Month":2,"Amount":649.31},{"AmountDue":-179.51,"AmountPayd":612.08,"Customer":93,"Year":2018,"Month":10,"Amount":791.59},{"AmountDue":-180.30,"AmountPayd":393.91,"Customer":63,"Year":2018,"Month":7,"Amount":574.21},{"AmountDue":-180.41,"AmountPayd":762.90,"Customer":55,"Year":2018,"Month":1,"Amount":943.31},{"AmountDue":-181.18,"AmountPayd":144.83,"Customer":97,"Year":2018,"Month":11,"Amount":326.01},{"AmountDue":-183.89,"AmountPayd":580.15,"Customer":92,"Year":2018,"Month":12,"Amount":764.04},{"AmountDue":-184.29,"AmountPayd":665.23,"Customer":61,"Year":2018,"Month":11,"Amount":849.52},{"AmountDue":-186.10,"AmountPayd":489.50,"Customer":43,"Year":2018,"Month":10,"Amount":675.60},{"AmountDue":-186.17,"AmountPayd":604.36,"Customer":44,"Year":2018,"Month":1,"Amount":790.53},{"AmountDue":-186.72,"AmountPayd":572.71,"Customer":99,"Year":2018,"Month":1,"Amount":759.43},{"AmountDue":-188.96,"AmountPayd":101.31,"Customer":27,"Year":2018,"Month":8,"Amount":290.27},{"AmountDue":-189.13,"AmountPayd":650.09,"Customer":38,"Year":2018,"Month":10,"Amount":839.22},{"AmountDue":-193.89,"AmountPayd":143.37,"Customer":42,"Year":2018,"Month":11,"Amount":337.26},{"AmountDue":-197.70,"AmountPayd":915.68,"Customer":12,"Year":2018,"Month":3,"Amount":1113.38},{"AmountDue":-199.63,"AmountPayd":480.73,"Customer":90,"Year":2018,"Month":3,"Amount":680.36},{"AmountDue":-202.48,"AmountPayd":332.21,"Customer":28,"Year":2018,"Month":11,"Amount":534.69},{"AmountDue":-205.62,"AmountPayd":269.57,"Customer":38,"Year":2018,"Month":1,"Amount":475.19},{"AmountDue":-213.12,"AmountPayd":272.11,"Customer":22,"Year":2018,"Month":10,"Amount":485.23},{"AmountDue":-215.57,"AmountPayd":195.01,"Customer":44,"Year":2018,"Month":4,"Amount":410.58},{"AmountDue":-215.78,"AmountPayd":636.23,"Customer":75,"Year":2018,"Month":10,"Amount":852.01},{"AmountDue":-216.71,"AmountPayd":66.91,"Customer":39,"Year":2018,"Month":11,"Amount":283.62},{"AmountDue":-223.34,"AmountPayd":710.14,"Customer":30,"Year":2018,"Month":6,"Amount":933.48},{"AmountDue":-225.10,"AmountPayd":303.22,"Customer":23,"Year":2018,"Month":5,"Amount":528.32},{"AmountDue":-225.71,"AmountPayd":330.79,"Customer":80,"Year":2018,"Month":4,"Amount":556.50},{"AmountDue":-225.80,"AmountPayd":20.56,"Customer":13,"Year":2018,"Month":9,"Amount":246.36},{"AmountDue":-230.54,"AmountPayd":199.73,"Customer":84,"Year":2018,"Month":4,"Amount":430.27},{"AmountDue":-231.59,"AmountPayd":158.72,"Customer":40,"Year":2018,"Month":11,"Amount":390.31},{"AmountDue":-234.91,"AmountPayd":318.48,"Customer":56,"Year":2018,"Month":4,"Amount":553.39},{"AmountDue":-237.90,"AmountPayd":510.56,"Customer":53,"Year":2018,"Month":10,"Amount":748.46},{"AmountDue":-238.38,"AmountPayd":0.0,"Customer":63,"Year":2018,"Month":9,"Amount":238.38},{"AmountDue":-240.74,"AmountPayd":581.33,"Customer":27,"Year":2018,"Month":6,"Amount":822.07},{"AmountDue":-241.16,"AmountPayd":827.75,"Customer":11,"Year":2018,"Month":7,"Amount":1068.91},{"AmountDue":-246.02,"AmountPayd":542.76,"Customer":51,"Year":2018,"Month":4,"Amount":788.78},{"AmountDue":-246.99,"AmountPayd":868.09,"Customer":29,"Year":2018,"Month":12,"Amount":1115.08},{"AmountDue":-251.11,"AmountPayd":206.88,"Customer":87,"Year":2018,"Month":8,"Amount":457.99},{"AmountDue":-251.18,"AmountPayd":171.98,"Customer":72,"Year":2018,"Month":8,"Amount":423.16},{"AmountDue":-263.11,"AmountPayd":345.95,"Customer":53,"Year":2018,"Month":1,"Amount":609.06},{"AmountDue":-264.95,"AmountPayd":145.80,"Customer":52,"Year":2018,"Month":2,"Amount":410.75},{"AmountDue":-272.07,"AmountPayd":211.04,"Customer":86,"Year":2018,"Month":10,"Amount":483.11},{"AmountDue":-273.39,"AmountPayd":251.77,"Customer":79,"Year":2018,"Month":2,"Amount":525.16},{"AmountDue":-275.24,"AmountPayd":161.92,"Customer":61,"Year":2018,"Month":5,"Amount":437.16},{"AmountDue":-279.04,"AmountPayd":302.30,"Customer":4,"Year":2018,"Month":12,"Amount":581.34},{"AmountDue":-281.34,"AmountPayd":320.47,"Customer":88,"Year":2018,"Month":11,"Amount":601.81},{"AmountDue":-288.89,"AmountPayd":264.07,"Customer":41,"Year":2018,"Month":11,"Amount":552.96},{"AmountDue":-291.11,"AmountPayd":425.44,"Customer":43,"Year":2018,"Month":6,"Amount":716.55},{"AmountDue":-293.74,"AmountPayd":324.19,"Customer":74,"Year":2018,"Month":12,"Amount":617.93},{"AmountDue":-294.76,"AmountPayd":404.12,"Customer":58,"Year":2018,"Month":7,"Amount":698.88},{"AmountDue":-295.27,"AmountPayd":259.30,"Customer":92,"Year":2018,"Month":3,"Amount":554.57},{"AmountDue":-295.57,"AmountPayd":281.30,"Customer":76,"Year":2018,"Month":5,"Amount":576.87},{"AmountDue":-303.41,"AmountPayd":177.72,"Customer":72,"Year":2018,"Month":6,"Amount":481.13},{"AmountDue":-305.92,"AmountPayd":566.23,"Customer":80,"Year":2018,"Month":7,"Amount":872.15},{"AmountDue":-305.93,"AmountPayd":153.08,"Customer":5,"Year":2018,"Month":7,"Amount":459.01},{"AmountDue":-306.49,"AmountPayd":517.78,"Customer":38,"Year":2018,"Month":7,"Amount":824.27},{"AmountDue":-309.98,"AmountPayd":325.97,"Customer":57,"Year":2018,"Month":6,"Amount":635.95},{"AmountDue":-312.50,"AmountPayd":133.49,"Customer":43,"Year":2018,"Month":2,"Amount":445.99},{"AmountDue":-321.76,"AmountPayd":359.98,"Customer":72,"Year":2018,"Month":3,"Amount":681.74},{"AmountDue":-322.41,"AmountPayd":416.71,"Customer":6,"Year":2018,"Month":6,"Amount":739.12},{"AmountDue":-327.15,"AmountPayd":425.43,"Customer":85,"Year":2018,"Month":7,"Amount":752.58},{"AmountDue":-327.48,"AmountPayd":523.30,"Customer":49,"Year":2018,"Month":3,"Amount":850.78},{"AmountDue":-330.67,"AmountPayd":297.04,"Customer":52,"Year":2018,"Month":1,"Amount":627.71},{"AmountDue":-336.99,"AmountPayd":322.49,"Customer":35,"Year":2018,"Month":5,"Amount":659.48},{"AmountDue":-339.18,"AmountPayd":383.87,"Customer":23,"Year":2018,"Month":1,"Amount":723.05},{"AmountDue":-340.64,"AmountPayd":152.99,"Customer":91,"Year":2018,"Month":7,"Amount":493.63},{"AmountDue":-342.89,"AmountPayd":488.28,"Customer":52,"Year":2018,"Month":12,"Amount":831.17},{"AmountDue":-343.86,"AmountPayd":291.55,"Customer":11,"Year":2018,"Month":12,"Amount":635.41},{"AmountDue":-348.43,"AmountPayd":290.95,"Customer":10,"Year":2018,"Month":8,"Amount":639.38},{"AmountDue":-350.84,"AmountPayd":94.63,"Customer":59,"Year":2018,"Month":9,"Amount":445.47},{"AmountDue":-352.16,"AmountPayd":549.21,"Customer":41,"Year":2018,"Month":3,"Amount":901.37},{"AmountDue":-360.06,"AmountPayd":429.07,"Customer":21,"Year":2018,"Month":11,"Amount":789.13},{"AmountDue":-360.07,"AmountPayd":411.81,"Customer":83,"Year":2018,"Month":9,"Amount":771.88},{"AmountDue":-362.76,"AmountPayd":26.83,"Customer":66,"Year":2018,"Month":3,"Amount":389.59},{"AmountDue":-366.28,"AmountPayd":252.89,"Customer":65,"Year":2018,"Month":3,"Amount":619.17},{"AmountDue":-366.35,"AmountPayd":455.94,"Customer":82,"Year":2018,"Month":2,"Amount":822.29},{"AmountDue":-374.89,"AmountPayd":386.79,"Customer":75,"Year":2018,"Month":4,"Amount":761.68},{"AmountDue":-381.08,"AmountPayd":81.68,"Customer":50,"Year":2018,"Month":9,"Amount":462.76},{"AmountDue":-385.02,"AmountPayd":209.39,"Customer":60,"Year":2018,"Month":7,"Amount":594.41},{"AmountDue":-387.80,"AmountPayd":298.44,"Customer":10,"Year":2018,"Month":1,"Amount":686.24},{"AmountDue":-389.56,"AmountPayd":146.17,"Customer":9,"Year":2018,"Month":9,"Amount":535.73},{"AmountDue":-395.94,"AmountPayd":701.87,"Customer":21,"Year":2018,"Month":5,"Amount":1097.81},{"AmountDue":-397.43,"AmountPayd":452.95,"Customer":48,"Year":2018,"Month":9,"Amount":850.38},{"AmountDue":-405.69,"AmountPayd":456.23,"Customer":1,"Year":2018,"Month":10,"Amount":861.92},{"AmountDue":-412.83,"AmountPayd":372.71,"Customer":87,"Year":2018,"Month":10,"Amount":785.54},{"AmountDue":-425.37,"AmountPayd":653.41,"Customer":33,"Year":2018,"Month":12,"Amount":1078.78},{"AmountDue":-427.33,"AmountPayd":128.18,"Customer":16,"Year":2018,"Month":10,"Amount":555.51},{"AmountDue":-427.82,"AmountPayd":670.25,"Customer":58,"Year":2018,"Month":4,"Amount":1098.07},{"AmountDue":-433.58,"AmountPayd":377.01,"Customer":4,"Year":2018,"Month":3,"Amount":810.59},{"AmountDue":-434.87,"AmountPayd":390.11,"Customer":3,"Year":2018,"Month":2,"Amount":824.98},{"AmountDue":-441.97,"AmountPayd":450.66,"Customer":72,"Year":2018,"Month":12,"Amount":892.63},{"AmountDue":-441.99,"AmountPayd":59.37,"Customer":63,"Year":2018,"Month":5,"Amount":501.36},{"AmountDue":-447.62,"AmountPayd":235.75,"Customer":71,"Year":2018,"Month":1,"Amount":683.37},{"AmountDue":-451.51,"AmountPayd":32.09,"Customer":59,"Year":2018,"Month":12,"Amount":483.60},{"AmountDue":-455.05,"AmountPayd":280.27,"Customer":92,"Year":2018,"Month":9,"Amount":735.32},{"AmountDue":-460.15,"AmountPayd":561.58,"Customer":37,"Year":2018,"Month":2,"Amount":1021.73},{"AmountDue":-460.26,"AmountPayd":386.52,"Customer":87,"Year":2018,"Month":4,"Amount":846.78},{"AmountDue":-460.75,"AmountPayd":205.89,"Customer":21,"Year":2018,"Month":8,"Amount":666.64},{"AmountDue":-469.21,"AmountPayd":542.85,"Customer":32,"Year":2018,"Month":5,"Amount":1012.06},{"AmountDue":-470.47,"AmountPayd":371.54,"Customer":16,"Year":2018,"Month":7,"Amount":842.01},{"AmountDue":-484.90,"AmountPayd":196.57,"Customer":46,"Year":2018,"Month":3,"Amount":681.47},{"AmountDue":-490.44,"AmountPayd":218.38,"Customer":2,"Year":2018,"Month":7,"Amount":708.82},{"AmountDue":-491.04,"AmountPayd":224.45,"Customer":100,"Year":2018,"Month":10,"Amount":715.49},{"AmountDue":-497.49,"AmountPayd":405.13,"Customer":78,"Year":2018,"Month":5,"Amount":902.62},{"AmountDue":-510.06,"AmountPayd":217.12,"Customer":3,"Year":2018,"Month":7,"Amount":727.18},{"AmountDue":-510.98,"AmountPayd":309.33,"Customer":32,"Year":2018,"Month":12,"Amount":820.31},{"AmountDue":-518.49,"AmountPayd":661.00,"Customer":18,"Year":2018,"Month":1,"Amount":1179.49},{"AmountDue":-522.89,"AmountPayd":291.11,"Customer":15,"Year":2018,"Month":7,"Amount":814.00},{"AmountDue":-534.32,"AmountPayd":538.58,"Customer":61,"Year":2018,"Month":9,"Amount":1072.90},{"AmountDue":-536.31,"AmountPayd":290.04,"Customer":64,"Year":2018,"Month":11,"Amount":826.35},{"AmountDue":-545.72,"AmountPayd":342.34,"Customer":24,"Year":2018,"Month":3,"Amount":888.06},{"AmountDue":-551.13,"AmountPayd":149.84,"Customer":55,"Year":2018,"Month":9,"Amount":700.97},{"AmountDue":-567.38,"AmountPayd":233.57,"Customer":20,"Year":2018,"Month":6,"Amount":800.95},{"AmountDue":-578.72,"AmountPayd":108.88,"Customer":58,"Year":2018,"Month":9,"Amount":687.60},{"AmountDue":-580.39,"AmountPayd":398.49,"Customer":86,"Year":2018,"Month":7,"Amount":978.88},{"AmountDue":-585.83,"AmountPayd":429.23,"Customer":68,"Year":2018,"Month":8,"Amount":1015.06},{"AmountDue":-587.64,"AmountPayd":343.85,"Customer":47,"Year":2018,"Month":12,"Amount":931.49},{"AmountDue":-623.21,"AmountPayd":382.70,"Customer":34,"Year":2018,"Month":12,"Amount":1005.91},{"AmountDue":-649.65,"AmountPayd":25.38,"Customer":26,"Year":2018,"Month":7,"Amount":675.03},{"AmountDue":-677.33,"AmountPayd":409.38,"Customer":57,"Year":2018,"Month":2,"Amount":1086.71}]